Workbook
Name UPDATE: 'Data Sheet'!$E$1

Sheet Profit & Loss
A1: ='Data Sheet'!B1 -> HINDUSTAN UNILEVER LTD | H1: =UPDATE | M1: SCREENER.IN
A3: Narration | B3: ='Data Sheet'!B16 -> 42825 | C3: ='Data Sheet'!C16 -> 43190 | D3: ='Data Sheet'!D16 -> 43555 | E3: ='Data Sheet'!E16 -> 43921 | F3: ='Data Sheet'!F16 -> 44286 | G3: ='Data Sheet'!G16 -> 44651 | H3: ='Data Sheet'!H16 -> 45016 | I3: ='Data Sheet'!I16 -> 45382 | ... K3: ='Data Sheet'!K16 -> 46112 | L3: Trailing | M3: Best Case | N3: Worst Case
A4: Sales | B4: ='Data Sheet'!B17 -> 33162 | C4: ='Data Sheet'!C17 -> 35545 | D4: ='Data Sheet'!D17 -> 39310 | E4: ='Data Sheet'!E17 -> 39783 | F4: ='Data Sheet'!F17 -> 47028 | G4: ='Data Sheet'!G17 -> 52446 | H4: ='Data Sheet'!H17 -> 60580 | I4: ='Data Sheet'!I17 -> 61896 | ... K4: ='Data Sheet'!K17 -> 64468 | L4: =SUM(Quarters!H4:K4) -> 65225 | M4: =$K4+M23*K4 -> 65843.745 | N4: =$K4+N23*L4 -> 65834.541
A5: Expenses | B5: =SUM('Data Sheet'!B18,'Data Sheet'!B20:B24,-1*'Data Sheet'!B19) -> 26834 | C5: =SUM('Data Sheet'!C18,'Data Sheet'!C20:C24,-1*'Data Sheet'!C19) -> 28046 | D5: =SUM('Data Sheet'!D18,'Data Sheet'!D20:D24,-1*'Data Sheet'!D19) -> 30430 | E5: =SUM('Data Sheet'!E18,'Data Sheet'!E20:E24,-1*'Data Sheet'!E19) -> 29922 | F5: =SUM('Data Sheet'!F18,'Data Sheet'!F20:F24,-1*'Data Sheet'!F19) -> 35402 | G5: =SUM('Data Sheet'!G18,'Data Sheet'!G20:G24,-1*'Data Sheet'!G19) -> 39589 | H5: =SUM('Data Sheet'!H18,'Data Sheet'!H20:H24,-1*'Data Sheet'!H19) -> 46433 | I5: =SUM('Data Sheet'!I18,'Data Sheet'!I20:I24,-1*'Data Sheet'!I19) -> 47237 | ... K5: =SUM('Data Sheet'!K18,'Data Sheet'!K20:K24,-1*'Data Sheet'!K19) -> 49429 | L5: =SUM(Quarters!H5:K5) -> 50108 | M5: =M4-M6 -> 50366.286 | N5: =N4-N6 -> 50576.269
A6: Operating Profit | B6: =B4-B5 -> 6328 | C6: =C4-C5 -> 7499 | D6: =D4-D5 -> 8880 | E6: =E4-E5 -> 9861 | F6: =F4-F5 -> 11626 | G6: =G4-G5 -> 12857 | H6: =H4-H5 -> 14147 | I6: =I4-I5 -> 14659 | ... K6: =K4-K5 -> 15039 | L6: =SUM(Quarters!H6:K6) -> 15117 | M6: =M4*M24 -> 15477.459 | N6: =N4*N24 -> 15258.271
A7: Other Income | B7: ='Data Sheet'!B25 -> 606 | C7: ='Data Sheet'!C25 -> 353 | D7: ='Data Sheet'!D25 -> 322 | E7: ='Data Sheet'!E25 -> 424 | F7: ='Data Sheet'!F25 -> 170 | G7: ='Data Sheet'!G25 -> 219 | H7: ='Data Sheet'!H25 -> 448 | I7: ='Data Sheet'!I25 -> 817 | ... K7: ='Data Sheet'!K25 -> 4923 | L7: =SUM(Quarters!H7:K7) -> 4894 | M7: 0 | N7: 0
A8: Depreciation | B8: ='Data Sheet'!B26 -> 432 | C8: ='Data Sheet'!C26 -> 520 | D8: ='Data Sheet'!D26 -> 565 | E8: ='Data Sheet'!E26 -> 1002 | F8: ='Data Sheet'!F26 -> 1074 | G8: ='Data Sheet'!G26 -> 1091 | H8: ='Data Sheet'!H26 -> 1137 | I8: ='Data Sheet'!I26 -> 1216 | ... K8: ='Data Sheet'!K26 -> 1333 | L8: =SUM(Quarters!H8:K8) -> 1368 | M8: =+$L8 -> 1368 | N8: =+$L8 -> 1368
A9: Interest | B9: ='Data Sheet'!B27 -> 35 | C9: ='Data Sheet'!C27 -> 26 | D9: ='Data Sheet'!D27 -> 33 | E9: ='Data Sheet'!E27 -> 118 | F9: ='Data Sheet'!F27 -> 117 | G9: ='Data Sheet'!G27 -> 106 | H9: ='Data Sheet'!H27 -> 114 | I9: ='Data Sheet'!I27 -> 334 | ... K9: ='Data Sheet'!K27 -> 410 | L9: =SUM(Quarters!H9:K9) -> 415 | M9: =+$L9 -> 415 | N9: =+$L9 -> 415
A10: Profit before tax | B10: ='Data Sheet'!B28 -> 6467 | C10: ='Data Sheet'!C28 -> 7306 | D10: ='Data Sheet'!D28 -> 8604 | E10: ='Data Sheet'!E28 -> 9165 | F10: ='Data Sheet'!F28 -> 10605 | G10: ='Data Sheet'!G28 -> 11879 | H10: ='Data Sheet'!H28 -> 13344 | I10: ='Data Sheet'!I28 -> 13926 | ... K10: ='Data Sheet'!K28 -> 18219 | L10: =SUM(Quarters!H10:K10) -> 18228 | M10: =M6+M7-SUM(M8:M9) -> 13694.459 | N10: =N6+N7-SUM(N8:N9) -> 13475.271
A11: Tax | B11: ='Data Sheet'!B29 -> 1977 | C11: ='Data Sheet'!C29 -> 2079 | D11: ='Data Sheet'!D29 -> 2544 | E11: ='Data Sheet'!E29 -> 2409 | F11: ='Data Sheet'!F29 -> 2606 | G11: ='Data Sheet'!G29 -> 2987 | H11: ='Data Sheet'!H29 -> 3201 | I11: ='Data Sheet'!I29 -> 3644 | ... K11: ='Data Sheet'!K29 -> 3160 | L11: =SUM(Quarters!H11:K11) -> 3169 | M11: =IF($L10>0,$L11/$L10,0) -> 0.17385341 | N11: =IF($L10>0,$L11/$L10,0) -> 0.17385341
A12: Net profit | B12: ='Data Sheet'!B30 -> 4476 | C12: ='Data Sheet'!C30 -> 5214 | D12: ='Data Sheet'!D30 -> 6054 | E12: ='Data Sheet'!E30 -> 6748 | F12: ='Data Sheet'!F30 -> 7995 | G12: ='Data Sheet'!G30 -> 8879 | H12: ='Data Sheet'!H30 -> 10120 | I12: ='Data Sheet'!I30 -> 10277 | ... K12: ='Data Sheet'!K30 -> 15040 | L12: =SUM(Quarters!H12:K12) -> 15040 | M12: =M10-M11*M10 -> 11313.63 | N12: =N10-N11*N10 -> 11132.55
A13: EPS | B13: =IF('Data Sheet'!B124>0,B12/'Data Sheet'!B124,0) -> 20.681052 | C13: =IF('Data Sheet'!C124>0,C12/'Data Sheet'!C124,0) -> 24.088704 | D13: =IF('Data Sheet'!D124>0,D12/'Data Sheet'!D124,0) -> 27.966924 | E13: =IF('Data Sheet'!E124>0,E12/'Data Sheet'!E124,0) -> 31.171471 | F13: =IF('Data Sheet'!F124>0,F12/'Data Sheet'!F124,0) -> 34.027068 | G13: =IF('Data Sheet'!G124>0,G12/'Data Sheet'!G124,0) -> 37.789411 | H13: =IF('Data Sheet'!H124>0,H12/'Data Sheet'!H124,0) -> 43.071161 | I13: =IF('Data Sheet'!I124>0,I12/'Data Sheet'!I124,0) -> 43.73936 | ... K13: =IF('Data Sheet'!K124>0,K12/'Data Sheet'!K124,0) -> 64.010895 | L13: =IF('Data Sheet'!$B6>0,'Profit & Loss'!L12/'Data Sheet'!$B6,0) -> 63.964656 | M13: =IF('Data Sheet'!$B6>0,'Profit & Loss'!M12/'Data Sheet'!$B6,0) -> 48.11652 | N13: =IF('Data Sheet'!$B6>0,'Profit & Loss'!N12/'Data Sheet'!$B6,0) -> 47.34639
A14: Price to earning | B14: =IF(B15>0,B15/B13,"") -> 42.193696 | C14: =IF(C15>0,C15/C13,"") -> 52.975453 | D14: =IF(D15>0,D15/D13,"") -> 58.409356 | E14: =IF(E15>0,E15/E13,"") -> 70.571903 | F14: =IF(F15>0,F15/F13,"") -> 68.390258 | G14: =IF(G15>0,G15/G13,"") -> 51.884905 | H14: =IF(H15>0,H15/H13,"") -> 56.892824 | I14: =IF(I15>0,I15/I13,"") -> 49.546678 | ... K14: =IF(K15>0,K15/K13,"") -> 32.107034 | L14: =IF(L13>0,L15/L13,0) -> 34.354128 | M14: =M25 -> 40.926914 | N14: =N25 -> 34.354128
A15: Price | B15: ='Data Sheet'!B121 -> 872.61 | C15: ='Data Sheet'!C121 -> 1276.11 | D15: ='Data Sheet'!D121 -> 1633.53 | E15: ='Data Sheet'!E121 -> 2199.83 | F15: ='Data Sheet'!F121 -> 2327.12 | G15: ='Data Sheet'!G121 -> 1960.7 | H15: ='Data Sheet'!H121 -> 2450.44 | I15: ='Data Sheet'!I121 -> 2167.14 | ... K15: ='Data Sheet'!K121 -> 2055.2 | L15: ='Data Sheet'!B8 -> 2197.45 | M15: =M13*M14 -> 1969.2607 | N15: =N13*N14 -> 1626.5439
A17: RATIOS:
A18: Dividend Payout | B18: =IF('Data Sheet'!B30>0,'Data Sheet'!B31/'Data Sheet'!B30,0) -> 0.82037534 | C18: =IF('Data Sheet'!C30>0,'Data Sheet'!C31/'Data Sheet'!C30,0) -> 0.82853855 | D18: =IF('Data Sheet'!D30>0,'Data Sheet'!D31/'Data Sheet'!D30,0) -> 0.78493558 | E18: =IF('Data Sheet'!E30>0,'Data Sheet'!E31/'Data Sheet'!E30,0) -> 0.80023711 | F18: =IF('Data Sheet'!F30>0,'Data Sheet'!F31/'Data Sheet'!F30,0) -> 1.1904315 | G18: =IF('Data Sheet'!G30>0,'Data Sheet'!G31/'Data Sheet'!G30,0) -> 0.89987611 | H18: =IF('Data Sheet'!H30>0,'Data Sheet'!H31/'Data Sheet'!H30,0) -> 0.90563241 | I18: =IF('Data Sheet'!I30>0,'Data Sheet'!I31/'Data Sheet'!I30,0) -> 0.960397 | ... K18: =IF('Data Sheet'!K30>0,'Data Sheet'!K31/'Data Sheet'!K30,0) -> 0.640625
A19: OPM | B19: =IF(B6>0,B6/B4,0) -> 0.19082082 | C19: =IF(C6>0,C6/C4,0) -> 0.21097201 | D19: =IF(D6>0,D6/D4,0) -> 0.22589672 | E19: =IF(E6>0,E6/E4,0) -> 0.24786969 | F19: =IF(F6>0,F6/F4,0) -> 0.24721443 | G19: =IF(G6>0,G6/G4,0) -> 0.24514739 | H19: =IF(H6>0,H6/H4,0) -> 0.23352592 | I19: =IF(I6>0,I6/I4,0) -> 0.23683275 | ... L19: =IF(L6>0,L6/L4,0) -> 0.23176696
G22: TRENDS: | H22: 10 YEARS | I22: 7 YEARS | J22: 5 YEARS | K22: 3 YEARS | L22: RECENT | M22: BEST | N22: WORST
G23: Sales Growth | H23: =IF(B4=0,"",POWER($K4/B4,1/9)-1) -> 0.076658974 | I23: =IF(D4=0,"",POWER($K4/D4,1/7)-1) -> 0.073227008 | J23: =IF(F4=0,"",POWER($K4/F4,1/5)-1) -> 0.065117542 | K23: =IF(H4=0,"",POWER($K4/H4,1/3)-1) -> 0.020951182 | L23: =IF(ISERROR(MAX(IF(J4=0,"",(K4-J4)/J4),IF(K4=0,"",(L4-K4)/K4))),"",MAX(IF(J4=0,"",(K4-J4)/J4),IF(K4=0,"",(L4-K4)/K4))) -> 0.021339966 | M23: =MAX(K23:L23) -> 0.021339966 | N23: =MIN(H23:L23) -> 0.020951182
G24: OPM | H24: =IF(SUM(B4:$K$4)=0,"",SUMPRODUCT(B19:$K$19,B4:$K$4)/SUM(B4:$K$4)) -> 0.23271652 | I24: =IF(SUM(E4:$K$4)=0,"",SUMPRODUCT(E19:$K$19,E4:$K$4)/SUM(E4:$K$4)) -> 0.23895901 | J24: =IF(SUM(G4:$K$4)=0,"",SUMPRODUCT(G19:$K$19,G4:$K$4)/SUM(G4:$K$4)) -> 0.2365038 | K24: =IF(SUM(I4:$K$4)=0,"",SUMPRODUCT(I19:$K$19,I4:$K$4)/SUM(I4:$K$4)) -> 0.23506346 | L24: =L19 -> 0.23176696 | M24: =MAX(K24:L24) -> 0.23506346 | N24: =MIN(H24:L24) -> 0.23176696
G25: Price to Earning | H25: =IF(ISERROR(AVERAGEIF(B14:$L14,">0")),"",AVERAGEIF(B14:$L14,">0")) -> 51.366005 | I25: =IF(ISERROR(AVERAGEIF(E14:$L14,">0")),"",AVERAGEIF(E14:$L14,">0")) -> 51.430943 | J25: =IF(ISERROR(AVERAGEIF(G14:$L14,">0")),"",AVERAGEIF(G14:$L14,">0")) -> 45.414231 | K25: =IF(ISERROR(AVERAGEIF(I14:$L14,">0")),"",AVERAGEIF(I14:$L14,">0")) -> 40.926914 | L25: =L14 -> 34.354128 | M25: =MAX(K25:L25) -> 40.926914 | N25: =MIN(H25:L25) -> 34.354128

Sheet Quarters
A1: ='Profit & Loss'!A1 -> HINDUSTAN UNILEVER LTD | E1: =UPDATE | J1: SCREENER.IN
A3: Narration | B3: ='Data Sheet'!B41 -> 45291 | C3: ='Data Sheet'!C41 -> 45382 | D3: ='Data Sheet'!D41 -> 45473 | E3: ='Data Sheet'!E41 -> 45565 | F3: ='Data Sheet'!F41 -> 45657 | G3: ='Data Sheet'!G41 -> 45747 | H3: ='Data Sheet'!H41 -> 45838 | I3: ='Data Sheet'!I41 -> 45930 | ... K3: ='Data Sheet'!K41 -> 46112
A4: Sales | B4: ='Data Sheet'!B42 -> 15567 | C4: ='Data Sheet'!C42 -> 15210 | D4: ='Data Sheet'!D42 -> 15707 | E4: ='Data Sheet'!E42 -> 15926 | F4: ='Data Sheet'!F42 -> 15556 | G4: ='Data Sheet'!G42 -> 15190 | H4: ='Data Sheet'!H42 -> 16514 | I4: ='Data Sheet'!I42 -> 15919 | ... K4: ='Data Sheet'!K42 -> 16351
A5: Expenses | B5: ='Data Sheet'!B43 -> 11902 | C5: ='Data Sheet'!C43 -> 11675 | D5: ='Data Sheet'!D43 -> 11965 | E5: ='Data Sheet'!E43 -> 12139 | F5: ='Data Sheet'!F43 -> 11867 | G5: ='Data Sheet'!G43 -> 11572 | H5: ='Data Sheet'!H43 -> 12797 | I5: ='Data Sheet'!I43 -> 12137 | ... K5: ='Data Sheet'!K43 -> 12514
A6: Operating Profit | B6: ='Data Sheet'!B50 -> 3665 | C6: ='Data Sheet'!C50 -> 3535 | D6: ='Data Sheet'!D50 -> 3742 | E6: ='Data Sheet'!E50 -> 3787 | F6: ='Data Sheet'!F50 -> 3689 | G6: ='Data Sheet'!G50 -> 3618 | H6: ='Data Sheet'!H50 -> 3717 | I6: ='Data Sheet'!I50 -> 3782 | ... K6: ='Data Sheet'!K50 -> 3837
A7: Other Income | B7: ='Data Sheet'!B44 -> 184 | C7: ='Data Sheet'!C44 -> 309 | D7: ='Data Sheet'!D44 -> 209 | E7: ='Data Sheet'!E44 -> 203 | F7: ='Data Sheet'!F44 -> 733 | G7: ='Data Sheet'!G44 -> 149 | H7: ='Data Sheet'!H44 -> 74 | I7: ='Data Sheet'!I44 -> 269 | ... K7: ='Data Sheet'!K44 -> 503
A8: Depreciation | B8: ='Data Sheet'!B45 -> 313 | C8: ='Data Sheet'!C45 -> 320 | D8: ='Data Sheet'!D45 -> 329 | E8: ='Data Sheet'!E45 -> 338 | F8: ='Data Sheet'!F45 -> 318 | G8: ='Data Sheet'!G45 -> 318 | H8: ='Data Sheet'!H45 -> 361 | I8: ='Data Sheet'!I45 -> 322 | ... K8: ='Data Sheet'!K45 -> 348
A9: Interest | B9: ='Data Sheet'!B46 -> 91 | C9: ='Data Sheet'!C46 -> 105 | D9: ='Data Sheet'!D46 -> 93 | E9: ='Data Sheet'!E46 -> 110 | F9: ='Data Sheet'!F46 -> 109 | G9: ='Data Sheet'!G46 -> 77 | H9: ='Data Sheet'!H46 -> 127 | I9: ='Data Sheet'!I46 -> 124 | ... K9: ='Data Sheet'!K46 -> 76
A10: Profit before tax | B10: ='Data Sheet'!B47 -> 3445 | C10: ='Data Sheet'!C47 -> 3419 | D10: ='Data Sheet'!D47 -> 3529 | E10: ='Data Sheet'!E47 -> 3542 | F10: ='Data Sheet'!F47 -> 3995 | G10: ='Data Sheet'!G47 -> 3372 | H10: ='Data Sheet'!H47 -> 3303 | I10: ='Data Sheet'!I47 -> 3605 | ... K10: ='Data Sheet'!K47 -> 3916
A11: Tax | B11: ='Data Sheet'!B48 -> 937 | C11: ='Data Sheet'!C48 -> 858 | D11: ='Data Sheet'!D48 -> 917 | E11: ='Data Sheet'!E48 -> 947 | F11: ='Data Sheet'!F48 -> 1006 | G11: ='Data Sheet'!G48 -> 897 | H11: ='Data Sheet'!H48 -> 535 | I11: ='Data Sheet'!I48 -> 911 | ... K11: ='Data Sheet'!K48 -> 922
A12: Net profit | B12: ='Data Sheet'!B49 -> 2509 | C12: ='Data Sheet'!C49 -> 2558 | D12: ='Data Sheet'!D49 -> 2610 | E12: ='Data Sheet'!E49 -> 2591 | F12: ='Data Sheet'!F49 -> 2984 | G12: ='Data Sheet'!G49 -> 2464 | H12: ='Data Sheet'!H49 -> 2756 | I12: ='Data Sheet'!I49 -> 2685 | ... K12: ='Data Sheet'!K49 -> 2992
A14: OPM | B14: =IF(B4>0,B6/B4,"") -> 0.23543393 | C14: =IF(C4>0,C6/C4,"") -> 0.23241289 | D14: =IF(D4>0,D6/D4,"") -> 0.23823773 | E14: =IF(E4>0,E6/E4,"") -> 0.23778727 | F14: =IF(F4>0,F6/F4,"") -> 0.23714322 | G14: =IF(G4>0,G6/G4,"") -> 0.23818302 | H14: =IF(H4>0,H6/H4,"") -> 0.22508175 | I14: =IF(I4>0,I6/I4,"") -> 0.23757774 | ... K14: =IF(K4>0,K6/K4,"") -> 0.23466455

Sheet Balance Sheet
A1: ='Profit & Loss'!A1 -> HINDUSTAN UNILEVER LTD | E1: =UPDATE | J1: SCREENER.IN
A3: Narration | B3: ='Data Sheet'!B56 -> 42825 | C3: ='Data Sheet'!C56 -> 43190 | D3: ='Data Sheet'!D56 -> 43555 | E3: ='Data Sheet'!E56 -> 43921 | F3: ='Data Sheet'!F56 -> 44286 | G3: ='Data Sheet'!G56 -> 44651 | H3: ='Data Sheet'!H56 -> 45016 | I3: ='Data Sheet'!I56 -> 45382 | ... K3: ='Data Sheet'!K56 -> 46112
A4: Equity Share Capital | B4: ='Data Sheet'!B57 -> 216 | C4: ='Data Sheet'!C57 -> 216 | D4: ='Data Sheet'!D57 -> 216 | E4: ='Data Sheet'!E57 -> 216 | F4: ='Data Sheet'!F57 -> 235 | G4: ='Data Sheet'!G57 -> 235 | H4: ='Data Sheet'!H57 -> 235 | I4: ='Data Sheet'!I57 -> 235 | ... K4: ='Data Sheet'!K57 -> 235
A5: Reserves | B5: ='Data Sheet'!B58 -> 6528 | C5: ='Data Sheet'!C58 -> 7065 | D5: ='Data Sheet'!D58 -> 7651 | E5: ='Data Sheet'!E58 -> 8013 | F5: ='Data Sheet'!F58 -> 47439 | G5: ='Data Sheet'!G58 -> 48826 | H5: ='Data Sheet'!H58 -> 50069 | I5: ='Data Sheet'!I58 -> 50983 | ... K5: ='Data Sheet'!K58 -> 48504
A6: Borrowings | B6: ='Data Sheet'!B59 -> 277 | C6: ='Data Sheet'!C59 -> 0 | D6: ='Data Sheet'!D59 -> 99 | E6: ='Data Sheet'!E59 -> 0 | F6: ='Data Sheet'!F59 -> 0 | G6: ='Data Sheet'!G59 -> 1043 | H6: ='Data Sheet'!H59 -> 1219 | I6: ='Data Sheet'!I59 -> 1484 | ... K6: ='Data Sheet'!K59 -> 1478
A7: Other Liabilities | B7: ='Data Sheet'!B60 -> 8685 | C7: ='Data Sheet'!C60 -> 10581 | D7: ='Data Sheet'!D60 -> 10663 | E7: ='Data Sheet'!E60 -> 11924 | F7: ='Data Sheet'!F60 -> 21066 | G7: ='Data Sheet'!G60 -> 20402 | H7: ='Data Sheet'!H60 -> 21554 | I7: ='Data Sheet'!I60 -> 25787 | ... K7: ='Data Sheet'!K60 -> 29535
A8: Total | B8: ='Data Sheet'!B61 -> 15706 | C8: ='Data Sheet'!C61 -> 17862 | D8: ='Data Sheet'!D61 -> 18629 | E8: ='Data Sheet'!E61 -> 20153 | F8: ='Data Sheet'!F61 -> 68740 | G8: ='Data Sheet'!G61 -> 70506 | H8: ='Data Sheet'!H61 -> 73077 | I8: ='Data Sheet'!I61 -> 78489 | ... K8: ='Data Sheet'!K61 -> 79752
A10: Net Block | B10: ='Data Sheet'!B62 -> 4419 | C10: ='Data Sheet'!C62 -> 4528 | D10: ='Data Sheet'!D62 -> 4715 | E10: ='Data Sheet'!E62 -> 5479 | F10: ='Data Sheet'!F62 -> 51443 | G10: ='Data Sheet'!G62 -> 51473 | H10: ='Data Sheet'!H62 -> 52678 | I10: ='Data Sheet'!I62 -> 53744 | ... K10: ='Data Sheet'!K62 -> 57428
A11: Capital Work in Progress | B11: ='Data Sheet'!B63 -> 229 | C11: ='Data Sheet'!C63 -> 461 | D11: ='Data Sheet'!D63 -> 406 | E11: ='Data Sheet'!E63 -> 597 | F11: ='Data Sheet'!F63 -> 745 | G11: ='Data Sheet'!G63 -> 1313 | H11: ='Data Sheet'!H63 -> 1132 | I11: ='Data Sheet'!I63 -> 1025 | ... K11: ='Data Sheet'!K63 -> 880
A12: Investments | B12: ='Data Sheet'!B64 -> 3794 | C12: ='Data Sheet'!C64 -> 2873 | D12: ='Data Sheet'!D64 -> 2716 | E12: ='Data Sheet'!E64 -> 1255 | F12: ='Data Sheet'!F64 -> 2709 | G12: ='Data Sheet'!G64 -> 3521 | H12: ='Data Sheet'!H64 -> 2882 | I12: ='Data Sheet'!I64 -> 4625 | ... K12: ='Data Sheet'!K64 -> 4359
A13: Other Assets | B13: ='Data Sheet'!B65 -> 7264 | C13: ='Data Sheet'!C65 -> 10000 | D13: ='Data Sheet'!D65 -> 10792 | E13: ='Data Sheet'!E65 -> 12822 | F13: ='Data Sheet'!F65 -> 13843 | G13: ='Data Sheet'!G65 -> 14199 | H13: ='Data Sheet'!H65 -> 16385 | I13: ='Data Sheet'!I65 -> 19095 | ... K13: ='Data Sheet'!K65 -> 17085
A14: Total | B14: ='Data Sheet'!B66 -> 15706 | C14: ='Data Sheet'!C66 -> 17862 | D14: ='Data Sheet'!D66 -> 18629 | E14: ='Data Sheet'!E66 -> 20153 | F14: ='Data Sheet'!F66 -> 68740 | G14: ='Data Sheet'!G66 -> 70506 | H14: ='Data Sheet'!H66 -> 73077 | I14: ='Data Sheet'!I66 -> 78489 | ... K14: ='Data Sheet'!K66 -> 79752
A16: Working Capital | B16: =B13-B7 -> -1421 | C16: =C13-C7 -> -581 | D16: =D13-D7 -> 129 | E16: =E13-E7 -> 898 | F16: =F13-F7 -> -7223 | G16: =G13-G7 -> -6203 | H16: =H13-H7 -> -5169 | I16: =I13-I7 -> -6692 | ... K16: =K13-K7 -> -12450
A17: Debtors | B17: ='Data Sheet'!B67 -> 1085 | C17: ='Data Sheet'!C67 -> 1310 | D17: ='Data Sheet'!D67 -> 1816 | E17: ='Data Sheet'!E67 -> 1149 | F17: ='Data Sheet'!F67 -> 1758 | G17: ='Data Sheet'!G67 -> 2236 | H17: ='Data Sheet'!H67 -> 3079 | I17: ='Data Sheet'!I67 -> 2997 | ... K17: ='Data Sheet'!K67 -> 3379
A18: Inventory | B18: ='Data Sheet'!B68 -> 2541 | C18: ='Data Sheet'!C68 -> 2513 | D18: ='Data Sheet'!D68 -> 2574 | E18: ='Data Sheet'!E68 -> 2767 | F18: ='Data Sheet'!F68 -> 3579 | G18: ='Data Sheet'!G68 -> 4096 | H18: ='Data Sheet'!H68 -> 4251 | I18: ='Data Sheet'!I68 -> 4022 | ... K18: ='Data Sheet'!K68 -> 4789
A20: Debtor Days | B20: =IF('Profit & Loss'!B4>0,'Balance Sheet'!B17/('Profit & Loss'!B4/365),0) -> 11.942133 | C20: =IF('Profit & Loss'!C4>0,'Balance Sheet'!C17/('Profit & Loss'!C4/365),0) -> 13.451962 | D20: =IF('Profit & Loss'!D4>0,'Balance Sheet'!D17/('Profit & Loss'!D4/365),0) -> 16.861867 | E20: =IF('Profit & Loss'!E4>0,'Balance Sheet'!E17/('Profit & Loss'!E4/365),0) -> 10.541814 | F20: =IF('Profit & Loss'!F4>0,'Balance Sheet'!F17/('Profit & Loss'!F4/365),0) -> 13.644425 | G20: =IF('Profit & Loss'!G4>0,'Balance Sheet'!G17/('Profit & Loss'!G4/365),0) -> 15.56153 | H20: =IF('Profit & Loss'!H4>0,'Balance Sheet'!H17/('Profit & Loss'!H4/365),0) -> 18.551255 | I20: =IF('Profit & Loss'!I4>0,'Balance Sheet'!I17/('Profit & Loss'!I4/365),0) -> 17.673275 | ... K20: =IF('Profit & Loss'!K4>0,'Balance Sheet'!K17/('Profit & Loss'!K4/365),0) -> 19.130964
A21: Inventory Turnover | B21: =IF('Balance Sheet'!B18>0,'Profit & Loss'!B4/'Balance Sheet'!B18,0) -> 13.050767 | C21: =IF('Balance Sheet'!C18>0,'Profit & Loss'!C4/'Balance Sheet'!C18,0) -> 14.144449 | D21: =IF('Balance Sheet'!D18>0,'Profit & Loss'!D4/'Balance Sheet'!D18,0) -> 15.27195 | E21: =IF('Balance Sheet'!E18>0,'Profit & Loss'!E4/'Balance Sheet'!E18,0) -> 14.377665 | F21: =IF('Balance Sheet'!F18>0,'Profit & Loss'!F4/'Balance Sheet'!F18,0) -> 13.139983 | G21: =IF('Balance Sheet'!G18>0,'Profit & Loss'!G4/'Balance Sheet'!G18,0) -> 12.804199 | H21: =IF('Balance Sheet'!H18>0,'Profit & Loss'!H4/'Balance Sheet'!H18,0) -> 14.250765 | I21: =IF('Balance Sheet'!I18>0,'Profit & Loss'!I4/'Balance Sheet'!I18,0) -> 15.389359 | ... K21: =IF('Balance Sheet'!K18>0,'Profit & Loss'!K4/'Balance Sheet'!K18,0) -> 13.461683
A23: Return on Equity | B23: =IF(SUM('Balance Sheet'!B4:B5)>0,'Profit & Loss'!B12/SUM('Balance Sheet'!B4:B5),"") -> 0.66370107 | C23: =IF(SUM('Balance Sheet'!C4:C5)>0,'Profit & Loss'!C12/SUM('Balance Sheet'!C4:C5),"") -> 0.71611042 | D23: =IF(SUM('Balance Sheet'!D4:D5)>0,'Profit & Loss'!D12/SUM('Balance Sheet'!D4:D5),"") -> 0.76954366 | E23: =IF(SUM('Balance Sheet'!E4:E5)>0,'Profit & Loss'!E12/SUM('Balance Sheet'!E4:E5),"") -> 0.82002673 | F23: =IF(SUM('Balance Sheet'!F4:F5)>0,'Profit & Loss'!F12/SUM('Balance Sheet'!F4:F5),"") -> 0.16770147 | G23: =IF(SUM('Balance Sheet'!G4:G5)>0,'Profit & Loss'!G12/SUM('Balance Sheet'!G4:G5),"") -> 0.18097878 | H23: =IF(SUM('Balance Sheet'!H4:H5)>0,'Profit & Loss'!H12/SUM('Balance Sheet'!H4:H5),"") -> 0.20117684 | I23: =IF(SUM('Balance Sheet'!I4:I5)>0,'Profit & Loss'!I12/SUM('Balance Sheet'!I4:I5),"") -> 0.20065211 | ... K23: =IF(SUM('Balance Sheet'!K4:K5)>0,'Profit & Loss'!K12/SUM('Balance Sheet'!K4:K5),"") -> 0.30858245
A24: Return on Capital Emp | C24: =IF((B4+B5+B6+C4+C5+C6)>0,('Profit & Loss'!C10+'Profit & Loss'!C9)*2/(B4+B5+B6+C4+C5+C6),"") -> 1.0253111 | D24: =IF((C4+C5+C6+D4+D5+D6)>0,('Profit & Loss'!D10+'Profit & Loss'!D9)*2/(C4+C5+C6+D4+D5+D6),"") -> 1.1329442 | E24: =IF((D4+D5+D6+E4+E5+E6)>0,('Profit & Loss'!E10+'Profit & Loss'!E9)*2/(D4+D5+D6+E4+E5+E6),"") -> 1.1464032 | F24: =IF((E4+E5+E6+F4+F5+F6)>0,('Profit & Loss'!F10+'Profit & Loss'!F9)*2/(E4+E5+E6+F4+F5+F6),"") -> 0.38359301 | G24: =IF((F4+F5+F6+G4+G5+G6)>0,('Profit & Loss'!G10+'Profit & Loss'!G9)*2/(F4+F5+F6+G4+G5+G6),"") -> 0.24514717 | H24: =IF((G4+G5+G6+H4+H5+H6)>0,('Profit & Loss'!H10+'Profit & Loss'!H9)*2/(G4+G5+G6+H4+H5+H6),"") -> 0.26485088 | I24: =IF((H4+H5+H6+I4+I5+I6)>0,('Profit & Loss'!I10+'Profit & Loss'!I9)*2/(H4+H5+H6+I4+I5+I6),"") -> 0.27363876 | J24: =IF((I4+I5+I6+J4+J5+J6)>0,('Profit & Loss'!J10+'Profit & Loss'!J9)*2/(I4+I5+I6+J4+J5+J6),"") -> 0.28548847 | K24: =IF((J4+J5+J6+K4+K5+K6)>0,('Profit & Loss'!K10+'Profit & Loss'!K9)*2/(J4+J5+J6+K4+K5+K6),"") -> 0.36791847

Sheet Cash Flow
A1: ='Balance Sheet'!A1 -> HINDUSTAN UNILEVER LTD | E1: =UPDATE | J1: SCREENER.IN
A3: Narration | B3: ='Data Sheet'!B81 -> 42825 | C3: ='Data Sheet'!C81 -> 43190 | D3: ='Data Sheet'!D81 -> 43555 | E3: ='Data Sheet'!E81 -> 43921 | F3: ='Data Sheet'!F81 -> 44286 | G3: ='Data Sheet'!G81 -> 44651 | H3: ='Data Sheet'!H81 -> 45016 | I3: ='Data Sheet'!I81 -> 45382 | ... K3: ='Data Sheet'!K81 -> 46112
A4: Cash from Operating Activity | B4: ='Data Sheet'!B113 -> 5185 | C4: ='Data Sheet'!C113 -> 6059 | D4: ='Data Sheet'!D113 -> 5800 | E4: ='Data Sheet'!E113 -> 7623 | F4: ='Data Sheet'!F113 -> 9163 | G4: ='Data Sheet'!G113 -> 9048 | H4: ='Data Sheet'!H113 -> 9991 | I4: ='Data Sheet'!I113 -> 15469 | ... K4: ='Data Sheet'!K113 -> 10999
A5: Cash from Investing Activity | B5: ='Data Sheet'!B114 -> -1173 | C5: ='Data Sheet'!C114 -> -1063 | D5: ='Data Sheet'!D114 -> -438 | E5: ='Data Sheet'!E114 -> 1791 | F5: ='Data Sheet'!F114 -> -1228 | G5: ='Data Sheet'!G114 -> -1728 | H5: ='Data Sheet'!H114 -> -1484 | I5: ='Data Sheet'!I114 -> -5324 | ... K5: ='Data Sheet'!K114 -> -3684
A6: Cash from Financing Activity | B6: ='Data Sheet'!B115 -> -4214 | C6: ='Data Sheet'!C115 -> -4975 | D6: ='Data Sheet'!D115 -> -5390 | E6: ='Data Sheet'!E115 -> -6819 | F6: ='Data Sheet'!F115 -> -9309 | G6: ='Data Sheet'!G115 -> -8015 | H6: ='Data Sheet'!H115 -> -8953 | I6: ='Data Sheet'!I115 -> -10034 | ... K6: ='Data Sheet'!K115 -> -10810
A7: Net Cash Flow | B7: ='Data Sheet'!B116 -> -202 | C7: ='Data Sheet'!C116 -> 21 | D7: ='Data Sheet'!D116 -> -28 | E7: ='Data Sheet'!E116 -> 2595 | F7: ='Data Sheet'!F116 -> -1374 | G7: ='Data Sheet'!G116 -> -695 | H7: ='Data Sheet'!H116 -> -446 | I7: ='Data Sheet'!I116 -> 111 | ... K7: ='Data Sheet'!K116 -> -3495

Sheet Customization
A1: How to use it?
A3: You can customize this workbook as you want.
B4: You can add custom formating, add conditional formating, add your own formulas… do ANYTHING.
B5: Please don't edit the "Data Sheet" only.
A7: After customization, you can upload this back on Screener.
B8: Upload on: | C8: https://www.screener.in/excel/
A10: Download your customized workbooks now onwards.
B11: Now whenever you will "Export to excel" from Screener, it will export your customized file.
A14: TESTING:
B15: This is a testing feature currently.
B16: You can report any formula errors on the worksheet at: support@screener.in

Sheet Data Sheet
A1: COMPANY NAME | B1: HINDUSTAN UNILEVER LTD | E1: =IF(B2<>B3,"A NEW VERSION OF THE WORKSHEET IS AVAILABLE","")
A2: LATEST VERSION | B2: 2.1 | E2: PLEASE DO NOT MAKE ANY CHANGES TO THIS SHEET
A3: CURRENT VERSION | B3: 2.1
A5: META
A6: Number of shares | B6: =IF(B9>0,B9/B8,0) -> 235.12985
A7: Face Value | B7: 1
A8: Current Price | B8: 2197.45
A9: Market Capitalization | B9: 516686.09
A15: PROFIT & LOSS
A16: Report Date | B16: 42825 | C16: 43190 | D16: 43555 | E16: 43921 | F16: 44286 | G16: 44651 | H16: 45016 | I16: 45382 | J16: 45747 | K16: 46112
A17: Sales | B17: 33162 | C17: 35545 | D17: 39310 | E17: 39783 | F17: 47028 | G17: 52446 | H17: 60580 | I17: 61896 | J17: 63121 | K17: 64468
A18: Raw Material Cost | B18: 13606 | C18: 14233 | D18: 15845 | E18: 15697 | F18: 20141 | G18: 22871 | H18: 28427 | I18: 26822 | J18: 27344 | K18: 32094
A19: Change in Inventory | B19: -144 | C19: 72 | D19: -12 | E19: 108 | F19: 405 | G19: 22 | H19: 75 | I19: 11 | J19: 153 | K19: 429
A20: Power and Fuel | B20: 295 | C20: 295 | D20: 308 | E20: 299 | F20: 339 | G20: 318 | H20: 384 | I20: 446 | J20: 427
A21: Other Mfr. Exp | B21: 2887 | C21: 2998 | D21: 3041 | E21: 2906 | F21: 2868 | G21: 3354 | H21: 3791 | I21: 3385 | J21: 3834
A22: Employee Cost | B22: 1743 | C22: 1860 | D22: 1875 | E22: 1820 | F22: 2358 | G22: 2545 | H22: 2854 | I22: 3009 | J22: 3077 | K22: 3175
A23: Selling and admin | B23: 6689 | C23: 7252 | D23: 7796 | E23: 7620 | F23: 7906 | G23: 8164 | H23: 8785 | I23: 10780 | J23: 10693 | K23: 6261
A24: Other Expenses | B24: 1470 | C24: 1480 | D24: 1553 | E24: 1688 | F24: 2195 | G24: 2359 | H24: 2267 | I24: 2806 | J24: 3056 | K24: 8328
A25: Other Income | B25: 606 | C25: 353 | D25: 322 | E25: 424 | F25: 170 | G25: 219 | H25: 448 | I25: 817 | J25: 1322 | K25: 4923
A26: Depreciation | B26: 432 | C26: 520 | D26: 565 | E26: 1002 | F26: 1074 | G26: 1091 | H26: 1137 | I26: 1216 | J26: 1355 | K26: 1333
A27: Interest | B27: 35 | C27: 26 | D27: 33 | E27: 118 | F27: 117 | G27: 106 | H27: 114 | I27: 334 | J27: 395 | K27: 410
A28: Profit before tax | B28: 6467 | C28: 7306 | D28: 8604 | E28: 9165 | F28: 10605 | G28: 11879 | H28: 13344 | I28: 13926 | J28: 14415 | K28: 18219
A29: Tax | B29: 1977 | C29: 2079 | D29: 2544 | E29: 2409 | F29: 2606 | G29: 2987 | H29: 3201 | I29: 3644 | J29: 3744 | K29: 3160
A30: Net profit | B30: 4476 | C30: 5214 | D30: 6054 | E30: 6748 | F30: 7995 | G30: 8879 | H30: 10120 | I30: 10277 | J30: 10649 | K30: 15040
A31: Dividend Amount | B31: 3672 | C31: 4320 | D31: 4752 | E31: 5400 | F31: 9517.5 | G31: 7990 | H31: 9165 | I31: 9870 | J31: 12455 | K31: 9635
A32: EBITDA | B32: =B28+B27+B26 -> 6934 | C32: =C28+C27+C26 -> 7852 | D32: =D28+D27+D26 -> 9202 | E32: =E28+E27+E26 -> 10285 | F32: =F28+F27+F26 -> 11796 | G32: =G28+G27+G26 -> 13076 | H32: =H28+H27+H26 -> 14595 | I32: =I28+I27+I26 -> 15476 | ... K32: =K28+K27+K26 -> 19962
A33: EBIT | B33: =B28+B27 -> 6502 | C33: =C28+C27 -> 7332 | D33: =D28+D27 -> 8637 | E33: =E28+E27 -> 9283 | F33: =F28+F27 -> 10722 | G33: =G28+G27 -> 11985 | H33: =H28+H27 -> 13458 | I33: =I28+I27 -> 14260 | ... K33: =K28+K27 -> 18629
A40: Quarters
A41: Report Date | B41: 45291 | C41: 45382 | D41: 45473 | E41: 45565 | F41: 45657 | G41: 45747 | H41: 45838 | I41: 45930 | J41: 46022 | K41: 46112
A42: Sales | B42: 15567 | C42: 15210 | D42: 15707 | E42: 15926 | F42: 15556 | G42: 15190 | H42: 16514 | I42: 15919 | J42: 16441 | K42: 16351
A43: Expenses | B43: 11902 | C43: 11675 | D43: 11965 | E43: 12139 | F43: 11867 | G43: 11572 | H43: 12797 | I43: 12137 | J43: 12660 | K43: 12514
A44: Other Income | B44: 184 | C44: 309 | D44: 209 | E44: 203 | F44: 733 | G44: 149 | H44: 74 | I44: 269 | J44: 4048 | K44: 503
A45: Depreciation | B45: 313 | C45: 320 | D45: 329 | E45: 338 | F45: 318 | G45: 318 | H45: 361 | I45: 322 | J45: 337 | K45: 348
A46: Interest | B46: 91 | C46: 105 | D46: 93 | E46: 110 | F46: 109 | G46: 77 | H46: 127 | I46: 124 | J46: 88 | K46: 76
A47: Profit before tax | B47: 3445 | C47: 3419 | D47: 3529 | E47: 3542 | F47: 3995 | G47: 3372 | H47: 3303 | I47: 3605 | J47: 7404 | K47: 3916
A48: Tax | B48: 937 | C48: 858 | D48: 917 | E48: 947 | F48: 1006 | G48: 897 | H48: 535 | I48: 911 | J48: 801 | K48: 922
A49: Net profit | B49: 2509 | C49: 2558 | D49: 2610 | E49: 2591 | F49: 2984 | G49: 2464 | H49: 2756 | I49: 2685 | J49: 6607 | K49: 2992
A50: Operating Profit | B50: 3665 | C50: 3535 | D50: 3742 | E50: 3787 | F50: 3689 | G50: 3618 | H50: 3717 | I50: 3782 | J50: 3781 | K50: 3837
A55: BALANCE SHEET
A56: Report Date | B56: 42825 | C56: 43190 | D56: 43555 | E56: 43921 | F56: 44286 | G56: 44651 | H56: 45016 | I56: 45382 | J56: 45747 | K56: 46112
A57: Equity Share Capital | B57: 216 | C57: 216 | D57: 216 | E57: 216 | F57: 235 | G57: 235 | H57: 235 | I57: 235 | J57: 235 | K57: 235
A58: Reserves | B58: 6528 | C58: 7065 | D58: 7651 | E58: 8013 | F58: 47439 | G58: 48826 | H58: 50069 | I58: 50983 | J58: 49167 | K58: 48504
A59: Borrowings | B59: 277 | D59: 99 | G59: 1043 | H59: 1219 | I59: 1484 | J59: 1648 | K59: 1478
A60: Other Liabilities | B60: 8685 | C60: 10581 | D60: 10663 | E60: 11924 | F60: 21066 | G60: 20402 | H60: 21554 | I60: 25787 | J60: 28813 | K60: 29535
A61: Total | B61: 15706 | C61: 17862 | D61: 18629 | E61: 20153 | F61: 68740 | G61: 70506 | H61: 73077 | I61: 78489 | J61: 79863 | K61: 79752
A62: Net Block | B62: 4419 | C62: 4528 | D62: 4715 | E62: 5479 | F62: 51443 | G62: 51473 | H62: 52678 | I62: 53744 | J62: 54335 | K62: 57428
A63: Capital Work in Progress | B63: 229 | C63: 461 | D63: 406 | E63: 597 | F63: 745 | G63: 1313 | H63: 1132 | I63: 1025 | J63: 1009 | K63: 880
A64: Investments | B64: 3794 | C64: 2873 | D64: 2716 | E64: 1255 | F64: 2709 | G64: 3521 | H64: 2882 | I64: 4625 | J64: 3810 | K64: 4359
A65: Other Assets | B65: 7264 | C65: 10000 | D65: 10792 | E65: 12822 | F65: 13843 | G65: 14199 | H65: 16385 | I65: 19095 | J65: 20709 | K65: 17085
A66: Total | B66: 15706 | C66: 17862 | D66: 18629 | E66: 20153 | F66: 68740 | G66: 70506 | H66: 73077 | I66: 78489 | J66: 79863 | K66: 79752
A67: Receivables | B67: 1085 | C67: 1310 | D67: 1816 | E67: 1149 | F67: 1758 | G67: 2236 | H67: 3079 | I67: 2997 | J67: 3819 | K67: 3379
A68: Inventory | B68: 2541 | C68: 2513 | D68: 2574 | E68: 2767 | F68: 3579 | G68: 4096 | H68: 4251 | I68: 4022 | J68: 4415 | K68: 4789
A69: Cash & Bank | B69: 1828 | C69: 3485 | D69: 3757 | E69: 5113 | F69: 4471 | G69: 3846 | H69: 4678 | I69: 7559 | J69: 7554 | K69: 3248
A70: No. of Equity Shares | B70: 2164349639 | C70: 2164528777 | D70: 2164704405 | E70: 2164704405 | F70: 2349567819 | G70: 2349591262 | H70: 2349591262 | I70: 2349591262 | J70: 2349591262
A71: New Bonus Shares
A72: Face value | B72: 1 | C72: 1 | D72: 1 | E72: 1 | F72: 1 | G72: 1 | H72: 1 | I72: 1 | J72: 1 | K72: 1
A80: CASH FLOW:
A81: Report Date | B81: 42825 | C81: 43190 | D81: 43555 | E81: 43921 | F81: 44286 | G81: 44651 | H81: 45016 | I81: 45382 | J81: 45747 | K81: 46112
A82: Cash from Operating Activity | B82: 5185 | C82: 6059 | D82: 5800 | E82: 7623 | F82: 9163 | G82: 9048 | H82: 9991 | I82: 15469 | J82: 11886 | K82: 10999
A83: Profit from Operations | B83: 6512 | C83: 7485 | D83: 8909 | E83: 9723 | F83: 11672 | G83: 12829 | H83: 14089 | I83: 14537 | J83: 14942 | K83: 151153
A84: Receivables | B84: 173 | C84: 0 | D84: 0 | E84: 0 | F84: 0 | G84: 0 | H84: 0 | I84: 0 | J84: 0 | K84: 0
A85: Inventory | B85: 37 | C85: -146 | D85: -195 | E85: -331 | F85: -543 | G85: -758 | H85: -339 | I85: 74 | J85: -584 | K85: -692
A86: Payables | B86: 501 | C86: 0 | D86: 0 | E86: 0 | F86: 0 | G86: 0 | H86: 0 | I86: 0 | J86: 0 | K86: 0
A87: Loans Advances | B87: 0 | C87: 0 | D87: 0 | E87: 0 | F87: 0 | G87: 0 | H87: 0 | I87: 0 | J87: 0 | K87: 0
A88: Operating Deposits | B88: -46 | C88: 0 | D88: 0 | E88: 0 | F88: 0 | G88: 0 | H88: 0 | I88: 0 | J88: 0 | K88: 0
A89: Other WC items | B89: -99 | C89: 982 | D89: -147 | E89: 742 | F89: 442 | G89: -242 | H89: -621 | I89: 1239 | J89: -204 | K89: 1378
A90: Working Capital changes | B90: 566 | C90: 836 | D90: -342 | E90: 411 | F90: -101 | G90: -1000 | H90: -960 | I90: 1313 | J90: -788 | K90: 686
A91: Direect Taxes | B91: -1859 | C91: -2264 | D91: -2767 | E91: -2505 | F91: -2407 | G91: -2784 | H91: -3138 | I91: -381 | J91: -2268 | K91: -4840
A92: Other operating items | B92: -21 | C92: 0 | D92: 0 | E92: 0 | F92: 0 | G92: 0 | H92: 0 | I92: 0 | J92: 0 | K92: 0
... A121: PRICE: | B121: 872.61 | C121: 1276.11 | D121: 1633.53 | E121: 2199.83 | F121: 2327.12 | G121: 1960.7 | H121: 2450.44 | I121: 2167.14 | J121: 2161.88 | K121: 2055.2
A123: DERIVED:
A124: Adjusted Equity Shares in Cr | B124: 216.43 | C124: 216.45 | D124: 216.47 | E124: 216.48 | F124: 234.96 | G124: 234.96 | H124: 234.96 | I124: 234.96 | J124: 234.96 | K124: 234.96

Sheet Historical FS
B2: ="Historical Financial Statements for "&'Data Sheet'!B1 -> Historical Financial Statements for HINDUSTAN UNILEVER LTD
B3: Year | C3: ='Data Sheet'!B16 -> 42825 | D3: ='Data Sheet'!C16 -> 43190 | E3: ='Data Sheet'!D16 -> 43555 | F3: ='Data Sheet'!E16 -> 43921 | G3: ='Data Sheet'!F16 -> 44286 | H3: ='Data Sheet'!G16 -> 44651 | I3: ='Data Sheet'!H16 -> 45016 | J3: ='Data Sheet'!I16 -> 45382 | ... L3: ='Data Sheet'!K16 -> 46112 | M3: ='Data Sheet'!K56+365 -> 46477 | N3: =M3+365 -> 46842 | O3: =N3+365 -> 47207 | P3: =O3+365 -> 47572
A5: # | B5: Income Statement | R5: CAGR
B6: ='Data Sheet'!A17 -> Sales | C6: ='Data Sheet'!B17 -> 33162 | D6: ='Data Sheet'!C17 -> 35545 | E6: ='Data Sheet'!D17 -> 39310 | F6: ='Data Sheet'!E17 -> 39783 | G6: ='Data Sheet'!F17 -> 47028 | H6: ='Data Sheet'!G17 -> 52446 | I6: ='Data Sheet'!H17 -> 60580 | ... L6: ='Data Sheet'!K17 -> 64468 | M6: =FORECAST(M$3,C6:L6,C$3:L$3) -> 71580.023 | N6: =FORECAST(N$3,D6:M6,D$3:M$3) -> 75897.69 | O6: =FORECAST(O$3,E6:N6,E$3:N$3) -> 80018.286 | P6: =FORECAST(P$3,F6:O6,F$3:O$3) -> 84102.444 | R6: =((L6/C6)^(1/10))-1 -> 0.068735777
B7: Sales Growth | C7: - | D7: =D6/C6-1 -> 0.071859357 | E7: =E6/D6-1 -> 0.10592207 | F7: =F6/E6-1 -> 0.012032562 | G7: =G6/F6-1 -> 0.18211296 | H7: =H6/G6-1 -> 0.11520796 | I7: =I6/H6-1 -> 0.15509286 | J7: =J6/I6-1 -> 0.021723341 | K7: =K6/J6-1 -> 0.019791263 | ... P7: =P6/O6-1 -> 0.051040306
B9: COGS | C9: =SUM('Data Sheet'!B18,'Data Sheet'!B20:B22)-(1*'Data Sheet'!B19) -> 18675 | D9: =SUM('Data Sheet'!C18,'Data Sheet'!C20:C22)-(1*'Data Sheet'!C19) -> 19314 | E9: =SUM('Data Sheet'!D18,'Data Sheet'!D20:D22)-(1*'Data Sheet'!D19) -> 21081 | F9: =SUM('Data Sheet'!E18,'Data Sheet'!E20:E22)-(1*'Data Sheet'!E19) -> 20614 | G9: =SUM('Data Sheet'!F18,'Data Sheet'!F20:F22)-(1*'Data Sheet'!F19) -> 25301 | H9: =SUM('Data Sheet'!G18,'Data Sheet'!G20:G22)-(1*'Data Sheet'!G19) -> 29066 | I9: =SUM('Data Sheet'!H18,'Data Sheet'!H20:H22)-(1*'Data Sheet'!H19) -> 35381 | J9: =SUM('Data Sheet'!I18,'Data Sheet'!I20:I22)-(1*'Data Sheet'!I19) -> 33651 | ... L9: =SUM('Data Sheet'!K18,'Data Sheet'!K20:K22)-(1*'Data Sheet'!K19) -> 34840 | M9: =FORECAST(M$3,C9:L9,C$3:L$3) -> 39339.249 | N9: =FORECAST(N$3,D9:M9,D$3:M$3) -> 41890.518 | O9: =FORECAST(O$3,E9:N9,E$3:N$3) -> 44256.027 | P9: =FORECAST(P$3,F9:O9,F$3:O$3) -> 46534.688
B11: Gross Profit | C11: =C6-C9 -> 14487 | D11: =D6-D9 -> 16231 | E11: =E6-E9 -> 18229 | F11: =F6-F9 -> 19169 | G11: =G6-G9 -> 21727 | H11: =H6-H9 -> 23380 | I11: =I6-I9 -> 25199 | J11: =J6-J9 -> 28245 | ... P11: =P6-P9 -> 37567.756
B12: Gross Profit Margins | C12: =C11/C6 -> 0.43685544 | D12: =D11/D6 -> 0.45663244 | E12: =E11/E6 -> 0.46372424 | F12: =F11/F6 -> 0.48183898 | G12: =G11/G6 -> 0.46200136 | H12: =H11/H6 -> 0.44579186 | I12: =I11/I6 -> 0.41596236 | J12: =J11/J6 -> 0.45632997 | ... P12: =P11/P6 -> 0.44669042
B14: Selling & General Expenses | C14: =SUM('Data Sheet'!B23:B24) -> 8159 | D14: =SUM('Data Sheet'!C23:C24) -> 8732 | E14: =SUM('Data Sheet'!D23:D24) -> 9349 | F14: =SUM('Data Sheet'!E23:E24) -> 9308 | G14: =SUM('Data Sheet'!F23:F24) -> 10101 | H14: =SUM('Data Sheet'!G23:G24) -> 10523 | I14: =SUM('Data Sheet'!H23:H24) -> 11052 | J14: =SUM('Data Sheet'!I23:I24) -> 13586 | ... L14: =SUM('Data Sheet'!K23:K24) -> 14589 | M14: =FORECAST(M$3,C14:L14,C$3:L$3) -> 14908.35 | N14: =FORECAST(N$3,D14:M14,D$3:M$3) -> 15770.563 | O14: =FORECAST(O$3,E14:N14,E$3:N$3) -> 16680.804 | P14: =FORECAST(P$3,F14:O14,F$3:O$3) -> 17650.803
B16: EBITDA | C16: =C11-C14 -> 6328 | D16: =D11-D14 -> 7499 | E16: =E11-E14 -> 8880 | F16: =F11-F14 -> 9861 | G16: =G11-G14 -> 11626 | H16: =H11-H14 -> 12857 | I16: =I11-I14 -> 14147 | J16: =J11-J14 -> 14659 | ... P16: =P11-P14 -> 19916.953
B17: EBITDA Margins | C17: =C16/C6 -> 0.19082082 | D17: =D16/D6 -> 0.21097201 | E17: =E16/E6 -> 0.22589672 | F17: =F16/F6 -> 0.24786969 | G17: =G16/G6 -> 0.24721443 | H17: =H16/H6 -> 0.24514739 | I17: =I16/I6 -> 0.23352592 | J17: =J16/J6 -> 0.23683275 | ... P17: =P16/P6 -> 0.23681777
B19: D&A | C19: ='Data Sheet'!B26 -> 432 | D19: ='Data Sheet'!C26 -> 520 | E19: ='Data Sheet'!D26 -> 565 | F19: ='Data Sheet'!E26 -> 1002 | G19: ='Data Sheet'!F26 -> 1074 | H19: ='Data Sheet'!G26 -> 1091 | I19: ='Data Sheet'!H26 -> 1137 | J19: ='Data Sheet'!I26 -> 1216 | ... L19: ='Data Sheet'!K26 -> 1333 | M19: =FORECAST(M$3,C19:L19,C$3:L$3) -> 1560.1091 | N19: =FORECAST(N$3,D19:M19,D$3:M$3) -> 1650.9876 | O19: =FORECAST(O$3,E19:N19,E$3:N$3) -> 1726.5137 | P19: =FORECAST(P$3,F19:O19,F$3:O$3) -> 1768.8664
B21: EBIT | C21: =C16-C19 -> 5896 | D21: =D16-D19 -> 6979 | E21: =E16-E19 -> 8315 | F21: =F16-F19 -> 8859 | G21: =G16-G19 -> 10552 | H21: =H16-H19 -> 11766 | I21: =I16-I19 -> 13010 | J21: =J16-J19 -> 13443 | ... P21: =P16-P19 -> 18148.087
B22: EBIT Margins | C22: =C21/C6 -> 0.17779386 | D22: =D21/D6 -> 0.19634266 | E22: =E21/E6 -> 0.21152379 | F22: =F21/F6 -> 0.22268306 | G22: =G21/G6 -> 0.22437697 | H22: =H21/H6 -> 0.22434504 | I22: =I21/I6 -> 0.21475735 | J22: =J21/J6 -> 0.21718689 | ... P22: =P21/P6 -> 0.21578549
B24: Interest | C24: ='Data Sheet'!B27 -> 35 | D24: ='Data Sheet'!C27 -> 26 | E24: ='Data Sheet'!D27 -> 33 | F24: ='Data Sheet'!E27 -> 118 | G24: ='Data Sheet'!F27 -> 117 | H24: ='Data Sheet'!G27 -> 106 | I24: ='Data Sheet'!H27 -> 114 | J24: ='Data Sheet'!I27 -> 334 | ... L24: ='Data Sheet'!K27 -> 410 | M24: =FORECAST(M$3,C24:L24,C$3:L$3) -> 416.76851 | N24: =FORECAST(N$3,D24:M24,D$3:M$3) -> 480.25104 | O24: =FORECAST(O$3,E24:N24,E$3:N$3) -> 541.29814 | P24: =FORECAST(P$3,F24:O24,F$3:O$3) -> 598.36985
B26: EBT | C26: =C21-C24 -> 5861 | D26: =D21-D24 -> 6953 | E26: =E21-E24 -> 8282 | F26: =F21-F24 -> 8741 | G26: =G21-G24 -> 10435 | H26: =H21-H24 -> 11660 | I26: =I21-I24 -> 12896 | J26: =J21-J24 -> 13109 | ... P26: =P21-P24 -> 17549.717
B27: EBT Margins | C27: =C26/C6 -> 0.17673844 | D27: =D26/D6 -> 0.1956112 | E27: =E26/E6 -> 0.2106843 | F27: =F26/F6 -> 0.21971696 | G27: =G26/G6 -> 0.22188909 | H27: =H26/H6 -> 0.22232391 | I27: =I26/I6 -> 0.21287554 | J27: =J26/J6 -> 0.21179075 | ... P27: =P26/P6 -> 0.20867071
B29: Tax | C29: ='Data Sheet'!B29 -> 1977 | D29: ='Data Sheet'!C29 -> 2079 | E29: ='Data Sheet'!D29 -> 2544 | F29: ='Data Sheet'!E29 -> 2409 | G29: ='Data Sheet'!F29 -> 2606 | H29: ='Data Sheet'!G29 -> 2987 | I29: ='Data Sheet'!H29 -> 3201 | J29: ='Data Sheet'!I29 -> 3644 | ... L29: ='Data Sheet'!K29 -> 3160 | M29: =FORECAST(M$3,C29:L29,C$3:L$3) -> 3853.5412 | N29: =FORECAST(N$3,D29:M29,D$3:M$3) -> 4032.0264 | O29: =FORECAST(O$3,E29:N29,E$3:N$3) -> 4184.0732 | P29: =FORECAST(P$3,F29:O29,F$3:O$3) -> 4390.804
B31: Net Profit | C31: =C26-C29 -> 3884 | D31: =D26-D29 -> 4874 | E31: =E26-E29 -> 5738 | F31: =F26-F29 -> 6332 | G31: =G26-G29 -> 7829 | H31: =H26-H29 -> 8673 | I31: =I26-I29 -> 9695 | J31: =J26-J29 -> 9465 | ... P31: =P26-P29 -> 13158.913
B32: Net Profit Margins | C32: =C31/C6 -> 0.11712201 | D32: =D31/D6 -> 0.13712196 | E32: =E31/E6 -> 0.14596795 | F32: =F31/F6 -> 0.15916346 | G32: =G31/G6 -> 0.16647529 | H32: =H31/H6 -> 0.16537009 | I32: =I31/I6 -> 0.16003632 | J32: =J31/J6 -> 0.1529178 | ... P32: =P31/P6 -> 0.15646291
A34: # | B34: Balance Sheet
B35: Equity Share Capital | C35: ='Data Sheet'!B57 -> 216 | D35: ='Data Sheet'!C57 -> 216 | E35: ='Data Sheet'!D57 -> 216 | F35: ='Data Sheet'!E57 -> 216 | G35: ='Data Sheet'!F57 -> 235 | H35: ='Data Sheet'!G57 -> 235 | I35: ='Data Sheet'!H57 -> 235 | J35: ='Data Sheet'!I57 -> 235 | ... L35: ='Data Sheet'!K57 -> 235 | M35: =FORECAST(M$3,C35:L35,C$3:L$3) -> 242.59678 | N35: =FORECAST(N$3,D35:M35,D$3:M$3) -> 245.63436 | O35: =FORECAST(O$3,E35:N35,E$3:N$3) -> 248.11505 | P35: =FORECAST(P$3,F35:O35,F$3:O$3) -> 249.61299
B36: Reserves | C36: ='Data Sheet'!B58 -> 6528 | D36: ='Data Sheet'!C58 -> 7065 | E36: ='Data Sheet'!D58 -> 7651 | F36: ='Data Sheet'!E58 -> 8013 | G36: ='Data Sheet'!F58 -> 47439 | H36: ='Data Sheet'!G58 -> 48826 | I36: ='Data Sheet'!H58 -> 50069 | J36: ='Data Sheet'!I58 -> 50983 | ... L36: ='Data Sheet'!K58 -> 48504 | M36: =FORECAST(M$3,C36:L36,C$3:L$3) -> 66307.82 | N36: =FORECAST(N$3,D36:M36,D$3:M$3) -> 72952.943 | O36: =FORECAST(O$3,E36:N36,E$3:N$3) -> 78416.614 | P36: =FORECAST(P$3,F36:O36,F$3:O$3) -> 81830.834
B37: Borrowings | C37: ='Data Sheet'!B59 -> 277 | D37: ='Data Sheet'!C59 -> 0 | E37: ='Data Sheet'!D59 -> 99 | F37: ='Data Sheet'!E59 -> 0 | G37: ='Data Sheet'!F59 -> 0 | H37: ='Data Sheet'!G59 -> 1043 | I37: ='Data Sheet'!H59 -> 1219 | J37: ='Data Sheet'!I59 -> 1484 | ... L37: ='Data Sheet'!K59 -> 1478 | M37: =FORECAST(M$3,C37:L37,C$3:L$3) -> 1856.8915 | N37: =FORECAST(N$3,D37:M37,D$3:M$3) -> 2190.1813 | O37: =FORECAST(O$3,E37:N37,E$3:N$3) -> 2477.7187 | P37: =FORECAST(P$3,F37:O37,F$3:O$3) -> 2760.7683
B38: Other Liabilities | C38: ='Data Sheet'!B60-C39 -> 2499 | D38: ='Data Sheet'!C60-D39 -> 3411 | E38: ='Data Sheet'!D60-E39 -> 3457 | F38: ='Data Sheet'!E60-F39 -> 4389 | G38: ='Data Sheet'!F60-G39 -> 12264 | H38: ='Data Sheet'!G60-H39 -> 11334 | I38: ='Data Sheet'!H60-I39 -> 11980 | J38: ='Data Sheet'!I60-J39 -> 15301 | ... L38: ='Data Sheet'!K60-L39 -> 16210 | M38: =FORECAST(M$3,C38:L38,C$3:L$3) -> 19934.85 | N38: =FORECAST(N$3,D38:M38,D$3:M$3) -> 22018.206 | O38: =FORECAST(O$3,E38:N38,E$3:N$3) -> 24016.48 | P38: =FORECAST(P$3,F38:O38,F$3:O$3) -> 25586.474
B39: Trade Payables | C39: 6186 | D39: 7170 | E39: 7206 | F39: 7535 | G39: 8802 | H39: 9068 | I39: 9574 | J39: 10486 | K39: 11315 | L39: 13325 | M39: =FORECAST(M$3,C39:L39,C$3:L$3) -> 12934.192 | N39: =FORECAST(N$3,D39:M39,D$3:M$3) -> 13712.711 | O39: =FORECAST(O$3,E39:N39,E$3:N$3) -> 14615.416 | P39: =FORECAST(P$3,F39:O39,F$3:O$3) -> 15452.955
B41: Total Liabilities | C41: =SUM(C35:C39) -> 15706 | D41: =SUM(D35:D39) -> 17862 | E41: =SUM(E35:E39) -> 18629 | F41: =SUM(F35:F39) -> 20153 | G41: =SUM(G35:G39) -> 68740 | H41: =SUM(H35:H39) -> 70506 | I41: =SUM(I35:I39) -> 73077 | J41: =SUM(J35:J39) -> 78489 | ... P41: =SUM(P35:P39) -> 125880.64
B43: Net Block | C43: ='Data Sheet'!B62 -> 4419 | D43: ='Data Sheet'!C62 -> 4528 | E43: ='Data Sheet'!D62 -> 4715 | F43: ='Data Sheet'!E62 -> 5479 | G43: ='Data Sheet'!F62 -> 51443 | H43: ='Data Sheet'!G62 -> 51473 | I43: ='Data Sheet'!H62 -> 52678 | J43: ='Data Sheet'!I62 -> 53744 | ... L43: ='Data Sheet'!K62 -> 57428 | M43: =FORECAST(M$3,C43:L43,C$3:L$3) -> 74432.432 | N43: =FORECAST(N$3,D43:M43,D$3:M$3) -> 82697.901 | O43: =FORECAST(O$3,E43:N43,E$3:N$3) -> 89634.283 | P43: =FORECAST(P$3,F43:O43,F$3:O$3) -> 94185.566
B44: Capital Work in Progress | C44: ='Data Sheet'!B63 -> 229 | D44: ='Data Sheet'!C63 -> 461 | E44: ='Data Sheet'!D63 -> 406 | F44: ='Data Sheet'!E63 -> 597 | G44: ='Data Sheet'!F63 -> 745 | H44: ='Data Sheet'!G63 -> 1313 | I44: ='Data Sheet'!H63 -> 1132 | J44: ='Data Sheet'!I63 -> 1025 | ... L44: ='Data Sheet'!K63 -> 880 | M44: =FORECAST(M$3,C44:L44,C$3:L$3) -> 1278.3516 | N44: =FORECAST(N$3,D44:M44,D$3:M$3) -> 1330.9431 | O44: =FORECAST(O$3,E44:N44,E$3:N$3) -> 1396.4998 | P44: =FORECAST(P$3,F44:O44,F$3:O$3) -> 1415.6257
B45: Investments | C45: ='Data Sheet'!B64 -> 3794 | D45: ='Data Sheet'!C64 -> 2873 | E45: ='Data Sheet'!D64 -> 2716 | F45: ='Data Sheet'!E64 -> 1255 | G45: ='Data Sheet'!F64 -> 2709 | H45: ='Data Sheet'!G64 -> 3521 | I45: ='Data Sheet'!H64 -> 2882 | J45: ='Data Sheet'!I64 -> 4625 | ... L45: ='Data Sheet'!K64 -> 4359 | M45: =FORECAST(M$3,C45:L45,C$3:L$3) -> 4150.2863 | N45: =FORECAST(N$3,D45:M45,D$3:M$3) -> 4652.3198 | O45: =FORECAST(O$3,E45:N45,E$3:N$3) -> 5085.9946 | P45: =FORECAST(P$3,F45:O45,F$3:O$3) -> 5532.8346
B46: Other Assets | C46: ='Data Sheet'!B65-SUM('Data Sheet'!B67:B69) -> 1810 | D46: ='Data Sheet'!C65-SUM('Data Sheet'!C67:C69) -> 2692 | E46: ='Data Sheet'!D65-SUM('Data Sheet'!D67:D69) -> 2645 | F46: ='Data Sheet'!E65-SUM('Data Sheet'!E67:E69) -> 3793 | G46: ='Data Sheet'!F65-SUM('Data Sheet'!F67:F69) -> 4035 | H46: ='Data Sheet'!G65-SUM('Data Sheet'!G67:G69) -> 4021 | I46: ='Data Sheet'!H65-SUM('Data Sheet'!H67:H69) -> 4377 | J46: ='Data Sheet'!I65-SUM('Data Sheet'!I67:I69) -> 4517 | ... L46: ='Data Sheet'!K65-SUM('Data Sheet'!K67:K69) -> 5669 | M46: =FORECAST(M$3,C46:L46,C$3:L$3) -> 5895.3513 | N46: =FORECAST(N$3,D46:M46,D$3:M$3) -> 6170.7334 | O46: =FORECAST(O$3,E46:N46,E$3:N$3) -> 6519.2032 | P46: =FORECAST(P$3,F46:O46,F$3:O$3) -> 6762.7107
B47: Total Non-Current Assets | C47: =SUM(C43:C46) -> 10252 | D47: =SUM(D43:D46) -> 10554 | E47: =SUM(E43:E46) -> 10482 | F47: =SUM(F43:F46) -> 11124 | G47: =SUM(G43:G46) -> 58932 | H47: =SUM(H43:H46) -> 60328 | I47: =SUM(I43:I46) -> 61069 | J47: =SUM(J43:J46) -> 63911 | ... P47: =SUM(P43:P46) -> 107896.74
B48: Receivables | C48: ='Data Sheet'!B67 -> 1085 | D48: ='Data Sheet'!C67 -> 1310 | E48: ='Data Sheet'!D67 -> 1816 | F48: ='Data Sheet'!E67 -> 1149 | G48: ='Data Sheet'!F67 -> 1758 | H48: ='Data Sheet'!G67 -> 2236 | I48: ='Data Sheet'!H67 -> 3079 | J48: ='Data Sheet'!I67 -> 2997 | ... L48: ='Data Sheet'!K67 -> 3379 | M48: =FORECAST(M$3,C48:L48,C$3:L$3) -> 3941.7874 | N48: =FORECAST(N$3,D48:M48,D$3:M$3) -> 4299.167 | O48: =FORECAST(O$3,E48:N48,E$3:N$3) -> 4669.1718 | P48: =FORECAST(P$3,F48:O48,F$3:O$3) -> 5122.9981
B49: Inventory | C49: ='Data Sheet'!B68 -> 2541 | D49: ='Data Sheet'!C68 -> 2513 | E49: ='Data Sheet'!D68 -> 2574 | F49: ='Data Sheet'!E68 -> 2767 | G49: ='Data Sheet'!F68 -> 3579 | H49: ='Data Sheet'!G68 -> 4096 | I49: ='Data Sheet'!H68 -> 4251 | J49: ='Data Sheet'!I68 -> 4022 | ... L49: ='Data Sheet'!K68 -> 4789 | M49: =FORECAST(M$3,C49:L49,C$3:L$3) -> 5079.5218 | N49: =FORECAST(N$3,D49:M49,D$3:M$3) -> 5419.0008 | O49: =FORECAST(O$3,E49:N49,E$3:N$3) -> 5717.6985 | P49: =FORECAST(P$3,F49:O49,F$3:O$3) -> 5958.5026
B50: Cash & Bank | C50: ='Data Sheet'!B69 -> 1828 | D50: ='Data Sheet'!C69 -> 3485 | E50: ='Data Sheet'!D69 -> 3757 | F50: ='Data Sheet'!E69 -> 5113 | G50: ='Data Sheet'!F69 -> 4471 | H50: ='Data Sheet'!G69 -> 3846 | I50: ='Data Sheet'!H69 -> 4678 | J50: ='Data Sheet'!I69 -> 7559 | ... L50: ='Data Sheet'!K69 -> 3248 | M50: =FORECAST(M$3,C50:L50,C$3:L$3) -> 6498.6198 | N50: =FORECAST(N$3,D50:M50,D$3:M$3) -> 6549.61 | O50: =FORECAST(O$3,E50:N50,E$3:N$3) -> 6751.4932 | P50: =FORECAST(P$3,F50:O50,F$3:O$3) -> 6902.4068
B51: Total Current Assets | C51: =SUM('Historical FS'!C48:C50) -> 5454 | D51: =SUM('Historical FS'!D48:D50) -> 7308 | E51: =SUM('Historical FS'!E48:E50) -> 8147 | F51: =SUM('Historical FS'!F48:F50) -> 9029 | G51: =SUM('Historical FS'!G48:G50) -> 9808 | H51: =SUM('Historical FS'!H48:H50) -> 10178 | I51: =SUM('Historical FS'!I48:I50) -> 12008 | J51: =SUM('Historical FS'!J48:J50) -> 14578 | ... P51: =SUM('Historical FS'!P48:P50) -> 17983.908
B53: Total Assets | C53: =SUM(C47,C51) -> 15706 | D53: =SUM(D47,D51) -> 17862 | E53: =SUM(E47,E51) -> 18629 | F53: =SUM(F47,F51) -> 20153 | G53: =SUM(G47,G51) -> 68740 | H53: =SUM(H47,H51) -> 70506 | I53: =SUM(I47,I51) -> 73077 | J53: =SUM(J47,J51) -> 78489 | ... P53: =SUM(P47,P51) -> 125880.64
B55: Shares Issued | C55: ='Data Sheet'!B70 -> 2164349639 | D55: ='Data Sheet'!C70 -> 2164528777 | E55: ='Data Sheet'!D70 -> 2164704405 | F55: ='Data Sheet'!E70 -> 2164704405 | G55: ='Data Sheet'!F70 -> 2349567819 | H55: ='Data Sheet'!G70 -> 2349591262 | I55: ='Data Sheet'!H70 -> 2349591262 | J55: ='Data Sheet'!I70 -> 2349591262 | ... L55: ='Data Sheet'!K70 -> 0 | M55: =FORECAST(M$3,C55:L55,C$3:L$3) -> 1.4839737e+09 | N55: =FORECAST(N$3,D55:M55,D$3:M$3) -> 1.2943858e+09 | O55: =FORECAST(O$3,E55:N55,E$3:N$3) -> 1.0743092e+09 | P55: =FORECAST(P$3,F55:O55,F$3:O$3) -> 8.2415866e+08
A58: # | B58: Cash Flow Statement
B59: Cash from Operating Activity
B60: Profit from Operations | C60: 6512 | D60: 7485 | E60: 8909 | F60: 9723 | G60: 11672 | H60: 12829 | I60: 14089 | J60: 14537 | K60: 14942 | L60: 151153 | M60: =FORECAST(M$3,C60:L60,C$3:L$3) -> 71717.614 | N60: =FORECAST(N$3,D60:M60,D$3:M$3) -> 85345.676 | O60: =FORECAST(O$3,E60:N60,E$3:N$3) -> 100341.88 | P60: =FORECAST(P$3,F60:O60,F$3:O$3) -> 116531.99
B61: Receivables | C61: 173 | D61: 0 | E61: 0 | F61: 0 | G61: 0 | H61: 0 | I61: 0 | J61: 0 | K61: 0 | L61: 0 | M61: =FORECAST(M$3,C61:L61,C$3:L$3) -> -34.585071 | N61: =FORECAST(N$3,D61:M61,D$3:M$3) -> -13.829437 | O61: =FORECAST(O$3,E61:N61,E$3:N$3) -> -17.055295 | P61: =FORECAST(P$3,F61:O61,F$3:O$3) -> -20.650967
B62: Inventory | C62: 37 | D62: -146 | E62: -195 | F62: -331 | G62: -543 | H62: -758 | I62: -339 | J62: 74 | K62: -584 | L62: -692 | M62: =FORECAST(M$3,C62:L62,C$3:L$3) -> -631.64273 | N62: =FORECAST(N$3,D62:M62,D$3:M$3) -> -642.63285 | O62: =FORECAST(O$3,E62:N62,E$3:N$3) -> -662.24713 | P62: =FORECAST(P$3,F62:O62,F$3:O$3) -> -669.66627
B63: Payables | C63: 501 | D63: 0 | E63: 0 | F63: 0 | G63: 0 | H63: 0 | I63: 0 | J63: 0 | K63: 0 | L63: 0 | M63: =FORECAST(M$3,C63:L63,C$3:L$3) -> -100.15677 | N63: =FORECAST(N$3,D63:M63,D$3:M$3) -> -40.04941 | O63: =FORECAST(O$3,E63:N63,E$3:N$3) -> -49.391347 | P63: =FORECAST(P$3,F63:O63,F$3:O$3) -> -59.804246
B64: Loans Advances | C64: 0 | D64: 0 | E64: 0 | F64: 0 | G64: 0 | H64: 0 | I64: 0 | J64: 0 | K64: 0 | L64: 0 | M64: =FORECAST(M$3,C64:L64,C$3:L$3) -> 0 | N64: =FORECAST(N$3,D64:M64,D$3:M$3) -> 0 | O64: =FORECAST(O$3,E64:N64,E$3:N$3) -> 0 | P64: =FORECAST(P$3,F64:O64,F$3:O$3) -> 0
B65: Operating Deposits | C65: -46 | D65: 0 | E65: 0 | F65: 0 | G65: 0 | H65: 0 | I65: 0 | J65: 0 | K65: 0 | L65: 0 | M65: =FORECAST(M$3,C65:L65,C$3:L$3) -> 9.1960304 | N65: =FORECAST(N$3,D65:M65,D$3:M$3) -> 3.6771914 | O65: =FORECAST(O$3,E65:N65,E$3:N$3) -> 4.5349341 | P65: =FORECAST(P$3,F65:O65,F$3:O$3) -> 5.4910086
B66: Other WC items | C66: -99 | D66: 982 | E66: -147 | F66: 742 | G66: 442 | H66: -242 | I66: -621 | J66: 1239 | K66: -204 | L66: 1378 | M66: =FORECAST(M$3,C66:L66,C$3:L$3) -> 585.35922 | N66: =FORECAST(N$3,D66:M66,D$3:M$3) -> 561.7843 | O66: =FORECAST(O$3,E66:N66,E$3:N$3) -> 771.37396 | P66: =FORECAST(P$3,F66:O66,F$3:O$3) -> 791.79286
B67: Working Capital changes | C67: 566 | D67: 836 | E67: -342 | F67: 411 | G67: -101 | H67: -1000 | I67: -960 | J67: 1313 | K67: -788 | L67: 686 | M67: =FORECAST(M$3,C67:L67,C$3:L$3) -> -171.82931 | N67: =FORECAST(N$3,D67:M67,D$3:M$3) -> -131.05021 | O67: =FORECAST(O$3,E67:N67,E$3:N$3) -> 47.215124 | P67: =FORECAST(P$3,F67:O67,F$3:O$3) -> 47.162388
B68: Direect Taxes | C68: -1859 | D68: -2264 | E68: -2767 | F68: -2505 | G68: -2407 | H68: -2784 | I68: -3138 | J68: -381 | K68: -2268 | L68: -4840 | M68: =FORECAST(M$3,C68:L68,C$3:L$3) -> -3094.3289 | N68: =FORECAST(N$3,D68:M68,D$3:M$3) -> -3146.9126 | O68: =FORECAST(O$3,E68:N68,E$3:N$3) -> -3246.1876 | P68: =FORECAST(P$3,F68:O68,F$3:O$3) -> -3460.5137
B69: Other operating items | C69: -21 | D69: 0 | E69: 0 | F69: 0 | G69: 0 | H69: 0 | I69: 0 | J69: 0 | K69: 0 | L69: 0 | M69: =FORECAST(M$3,C69:L69,C$3:L$3) -> 4.1981878 | N69: =FORECAST(N$3,D69:M69,D$3:M$3) -> 1.6787178 | O69: =FORECAST(O$3,E69:N69,E$3:N$3) -> 2.070296 | P69: =FORECAST(P$3,F69:O69,F$3:O$3) -> 2.5067648
B70: Exceptional CF items | C70: -13 | D70: 2 | E70: 0 | F70: -6 | G70: -1 | H70: 3 | I70: 0 | J70: 0 | K70: 0 | L70: 0 | M70: =FORECAST(M$3,C70:L70,C$3:L$3) -> 2.6649409 | N70: =FORECAST(N$3,D70:M70,D$3:M$3) -> 1.264959 | O70: =FORECAST(O$3,E70:N70,E$3:N$3) -> 2.2598045 | P70: =FORECAST(P$3,F70:O70,F$3:O$3) -> 3.1686861
B71: Cash Flow from Operating Activities | C71: 5185 | D71: 6059 | E71: 5800 | F71: 7623 | G71: 9163 | H71: 9048 | I71: 9991 | J71: 15469 | K71: 11886 | L71: 10999 | M71: =FORECAST(M$3,C71:L71,C$3:L$3) -> 14070.055 | N71: =FORECAST(N$3,D71:M71,D$3:M$3) -> 14998.869 | O71: =FORECAST(O$3,E71:N71,E$3:N$3) -> 15940.273 | P71: =FORECAST(P$3,F71:O71,F$3:O$3) -> 16593.45
B73: Cash from Investing Activity
B74: Fixed Asset Purchased | C74: -1113 | D74: -895 | E74: -767 | F74: -862 | G74: -4613 | H74: -1228 | I74: -1192 | J74: -1477 | K74: -1275 | L74: -1360 | M74: =FORECAST(M$3,C74:L74,C$3:L$3) -> -1679.5303 | N74: =FORECAST(N$3,D74:M74,D$3:M$3) -> -1662.6868 | O74: =FORECAST(O$3,E74:N74,E$3:N$3) -> -1543.2189 | P74: =FORECAST(P$3,F74:O74,F$3:O$3) -> -1290.5551
B75: Fixed Assets Sold | C75: 176 | D75: 32 | E75: 13 | F75: 52 | G75: 97 | H75: 175 | I75: 181 | J75: 20 | K75: 13 | L75: 29 | M75: =FORECAST(M$3,C75:L75,C$3:L$3) -> 46.932869 | N75: =FORECAST(N$3,D75:M75,D$3:M$3) -> 60.099476 | O75: =FORECAST(O$3,E75:N75,E$3:N$3) -> 48.745624 | P75: =FORECAST(P$3,F75:O75,F$3:O$3) -> 25.901801
B76: Investments purchased | C76: -31214 | D76: -51855 | E76: -74365 | F76: -36090 | G76: -39920 | H76: -48522 | I76: -22649 | J76: -21337 | K76: -22957 | L76: -25529 | M76: =FORECAST(M$3,C76:L76,C$3:L$3) -> -19100.514 | N76: =FORECAST(N$3,D76:M76,D$3:M$3) -> -10105.722 | O76: =FORECAST(O$3,E76:N76,E$3:N$3) -> -3821.3238 | P76: =FORECAST(P$3,F76:O76,F$3:O$3) -> -3808.3634
B77: Investments sold | C77: 30083 | D77: 52897 | E77: 74691 | F77: 37690 | G77: 38486 | H77: 47786 | I77: 23462 | J77: 19846 | K77: 23987 | L77: 25415 | M77: =FORECAST(M$3,C77:L77,C$3:L$3) -> 19034.949 | N77: =FORECAST(N$3,D77:M77,D$3:M$3) -> 9718.8104 | O77: =FORECAST(O$3,E77:N77,E$3:N$3) -> 3492.792 | P77: =FORECAST(P$3,F77:O77,F$3:O$3) -> 3465.9088
B78: Interest received | C78: 264 | D78: 297 | E78: 289 | F78: 351 | G78: 277 | H78: 161 | I78: 259 | J78: 425 | K78: 835 | L78: 428 | M78: =FORECAST(M$3,C78:L78,C$3:L$3) -> 542.92111 | N78: =FORECAST(N$3,D78:M78,D$3:M$3) -> 591.4038 | O78: =FORECAST(O$3,E78:N78,E$3:N$3) -> 649.5001 | P78: =FORECAST(P$3,F78:O78,F$3:O$3) -> 709.09868
B79: Dividends received | C79: 14 | D79: 0 | E79: 1 | F79: 1 | G79: 1 | H79: 1 | I79: 2 | J79: 3 | K79: 0 | L79: 5 | M79: =FORECAST(M$3,C79:L79,C$3:L$3) -> 0.53408672 | N79: =FORECAST(N$3,D79:M79,D$3:M$3) -> 2.6134011 | O79: =FORECAST(O$3,E79:N79,E$3:N$3) -> 2.6898469 | P79: =FORECAST(P$3,F79:O79,F$3:O$3) -> 2.8893574
B80: Redemp n Canc of Shares | C80: 20 | D80: 73 | E80: 0 | F80: 0 | G80: 0 | H80: 0 | I80: 0 | J80: 0 | K80: 0 | L80: 0 | M80: =FORECAST(M$3,C80:L80,C$3:L$3) -> -13.729668 | N80: =FORECAST(N$3,D80:M80,D$3:M$3) -> -20.085682 | O80: =FORECAST(O$3,E80:N80,E$3:N$3) -> -12.606874 | P80: =FORECAST(P$3,F80:O80,F$3:O$3) -> -15.396184
B81: Acquisition of companies | C81: 0 | D81: 0 | E81: 0 | F81: 0 | G81: 0 | H81: 0 | I81: -334 | J81: 0 | K81: 0 | L81: 0 | M81: =FORECAST(M$3,C81:L81,C$3:L$3) -> -66.770076 | N81: =FORECAST(N$3,D81:M81,D$3:M$3) -> -71.209966 | O81: =FORECAST(O$3,E81:N81,E$3:N$3) -> -72.976658 | P81: =FORECAST(P$3,F81:O81,F$3:O$3) -> -70.701793
B82: Other investing items | C82: 597 | D82: -1612 | E82: -300 | F82: 649 | G82: 3994 | H82: -101 | I82: -1213 | J82: -2804 | K82: 5870 | L82: -2672 | M82: =FORECAST(M$3,C82:L82,C$3:L$3) -> 266.15608 | N82: =FORECAST(N$3,D82:M82,D$3:M$3) -> 371.23761 | O82: =FORECAST(O$3,E82:N82,E$3:N$3) -> -48.528942 | P82: =FORECAST(P$3,F82:O82,F$3:O$3) -> -418.7423
B83: Cash Flow from investing Activities | C83: -1173 | D83: -1063 | E83: -438 | F83: 1791 | G83: -1228 | H83: -1728 | I83: -1484 | J83: -5324 | K83: 6473 | L83: -3684 | M83: =FORECAST(M$3,C83:L83,C$3:L$3) -> -939.0372 | N83: =FORECAST(N$3,D83:M83,D$3:M$3) -> -1103.5129 | O83: =FORECAST(O$3,E83:N83,E$3:N$3) -> -1320.0873 | P83: =FORECAST(P$3,F83:O83,F$3:O$3) -> -1453.998
B85: Cash from Financing Activity
B86: Proceeds from shares | C86: 0 | D86: 0 | E86: 0 | F86: 0 | G86: 0 | H86: 0 | I86: 0 | J86: 0 | K86: 0 | L86: 0 | M86: =FORECAST(M$3,C86:L86,C$3:L$3) -> 0 | N86: =FORECAST(N$3,D86:M86,D$3:M$3) -> 0 | O86: =FORECAST(O$3,E86:N86,E$3:N$3) -> 0 | P86: =FORECAST(P$3,F86:O86,F$3:O$3) -> 0
B87: Proceeds from borrowings | C87: 460 | D87: 0 | E87: 99 | F87: 0 | G87: 188 | H87: 55 | I87: 286 | J87: 0 | K87: 0 | L87: 0 | M87: =FORECAST(M$3,C87:L87,C$3:L$3) -> -21.518572 | N87: =FORECAST(N$3,D87:M87,D$3:M$3) -> 19.986219 | O87: =FORECAST(O$3,E87:N87,E$3:N$3) -> -12.446812 | P87: =FORECAST(P$3,F87:O87,F$3:O$3) -> -32.796866
B88: Repayment of borrowings | C88: -360 | D88: -277 | E88: 0 | F88: -99 | G88: -188 | H88: -55 | I88: -208 | J88: -85 | K88: 0 | L88: -46 | M88: =FORECAST(M$3,C88:L88,C$3:L$3) -> 6.3685193 | N88: =FORECAST(N$3,D88:M88,D$3:M$3) -> 0.78743441 | O88: =FORECAST(O$3,E88:N88,E$3:N$3) -> -9.3171266 | P88: =FORECAST(P$3,F88:O88,F$3:O$3) -> 31.891202
B89: Interest paid fin | C89: -14 | D89: -6 | E89: -7 | F89: -90 | G89: -92 | H89: -82 | I89: -88 | J89: -110 | K89: -130 | L89: -133 | M89: =FORECAST(M$3,C89:L89,C$3:L$3) -> -156.457 | N89: =FORECAST(N$3,D89:M89,D$3:M$3) -> -172.63376 | O89: =FORECAST(O$3,E89:N89,E$3:N$3) -> -183.65754 | P89: =FORECAST(P$3,F89:O89,F$3:O$3) -> -188.25039
B90: Dividends paid | C90: -3572 | D90: -3911 | E90: -4554 | F90: -5196 | G90: -8811 | H90: -7526 | I90: -8474 | J90: -9416 | K90: -12473 | L90: -10124 | M90: =FORECAST(M$3,C90:L90,C$3:L$3) -> -12463.513 | N90: =FORECAST(N$3,D90:M90,D$3:M$3) -> -13463.945 | O90: =FORECAST(O$3,E90:N90,E$3:N$3) -> -14362.563 | P90: =FORECAST(P$3,F90:O90,F$3:O$3) -> -15155.527
B91: Financial liabilities | C91: 0 | D91: 0 | E91: 0 | F91: -373 | G91: -406 | H91: -407 | I91: -467 | J91: -423 | K91: -498 | L91: -507 | M91: =FORECAST(M$3,C91:L91,C$3:L$3) -> -656.28193 | N91: =FORECAST(N$3,D91:M91,D$3:M$3) -> -713.37441 | O91: =FORECAST(O$3,E91:N91,E$3:N$3) -> -749.57671 | P91: =FORECAST(P$3,F91:O91,F$3:O$3) -> -752.7029
B92: Other financing items | C92: -728 | D92: -781 | E92: -928 | F92: -1061 | G92: 0 | H92: 0 | I92: -2 | J92: 0 | K92: 0 | L92: 0 | M92: =FORECAST(M$3,C92:L92,C$3:L$3) -> 311.05232 | N92: =FORECAST(N$3,D92:M92,D$3:M$3) -> 474.60954 | O92: =FORECAST(O$3,E92:N92,E$3:N$3) -> 620.24719 | P92: =FORECAST(P$3,F92:O92,F$3:O$3) -> 701.26979
B93: Cash Flow from Financing Activities | C93: -4214 | D93: -4975 | E93: -5390 | F93: -6819 | G93: -9309 | H93: -8015 | I93: -8953 | J93: -10034 | K93: -13101 | L93: -10810 | M93: =FORECAST(M$3,C93:L93,C$3:L$3) -> -12980.35 | N93: =FORECAST(N$3,D93:M93,D$3:M$3) -> -13854.57 | O93: =FORECAST(O$3,E93:N93,E$3:N$3) -> -14697.314 | P93: =FORECAST(P$3,F93:O93,F$3:O$3) -> -15396.116
B95: Net Cash Flow | C95: =C71+C83+C93 -> -202 | D95: =D71+D83+D93 -> 21 | E95: =E71+E83+E93 -> -28 | F95: =F71+F83+F93 -> 2595 | G95: =G71+G83+G93 -> -1374 | H95: =H71+H83+H93 -> -695 | I95: =I71+I83+I93 -> -446 | J95: =J71+J83+J93 -> 111 | ... P95: =P71+P83+P93 -> -256.66439

Sheet Ratio Analysis
B2: ="Ratio Analysis for "&'Data Sheet'!B1 -> Ratio Analysis for HINDUSTAN UNILEVER LTD
B3: Year | C3: ='Data Sheet'!B16 -> 42825 | D3: ='Data Sheet'!C16 -> 43190 | E3: ='Data Sheet'!D16 -> 43555 | F3: ='Data Sheet'!E16 -> 43921 | G3: ='Data Sheet'!F16 -> 44286 | H3: ='Data Sheet'!G16 -> 44651 | I3: ='Data Sheet'!H16 -> 45016 | J3: ='Data Sheet'!I16 -> 45382 | ... L3: ='Data Sheet'!K16 -> 46112 | M3: ='Data Sheet'!K56+365 -> 46477 | N3: =M3+365 -> 46842 | O3: =N3+365 -> 47207 | P3: =O3+365 -> 47572
B4: Profitability Ratios
B5: Gross Profit Margin | C5: ='Historical FS'!C12 -> 0.43685544 | D5: ='Historical FS'!D12 -> 0.45663244 | E5: ='Historical FS'!E12 -> 0.46372424 | F5: ='Historical FS'!F12 -> 0.48183898 | G5: ='Historical FS'!G12 -> 0.46200136 | H5: ='Historical FS'!H12 -> 0.44579186 | I5: ='Historical FS'!I12 -> 0.41596236 | J5: ='Historical FS'!J12 -> 0.45632997 | ... P5: ='Historical FS'!P12 -> 0.44669042
B6: EBITDA Margins | C6: ='Historical FS'!C17 -> 0.19082082 | D6: ='Historical FS'!D17 -> 0.21097201 | E6: ='Historical FS'!E17 -> 0.22589672 | F6: ='Historical FS'!F17 -> 0.24786969 | G6: ='Historical FS'!G17 -> 0.24721443 | H6: ='Historical FS'!H17 -> 0.24514739 | I6: ='Historical FS'!I17 -> 0.23352592 | J6: ='Historical FS'!J17 -> 0.23683275 | ... P6: ='Historical FS'!P17 -> 0.23681777
B7: EBIT Margins | C7: ='Historical FS'!C22 -> 0.17779386 | D7: ='Historical FS'!D22 -> 0.19634266 | E7: ='Historical FS'!E22 -> 0.21152379 | F7: ='Historical FS'!F22 -> 0.22268306 | G7: ='Historical FS'!G22 -> 0.22437697 | H7: ='Historical FS'!H22 -> 0.22434504 | I7: ='Historical FS'!I22 -> 0.21475735 | J7: ='Historical FS'!J22 -> 0.21718689 | ... P7: ='Historical FS'!P22 -> 0.21578549
B8: Net Profit Margins | C8: ='Historical FS'!C32 -> 0.11712201 | D8: ='Historical FS'!D32 -> 0.13712196 | E8: ='Historical FS'!E32 -> 0.14596795 | F8: ='Historical FS'!F32 -> 0.15916346 | G8: ='Historical FS'!G32 -> 0.16647529 | H8: ='Historical FS'!H32 -> 0.16537009 | I8: ='Historical FS'!I32 -> 0.16003632 | J8: ='Historical FS'!J32 -> 0.1529178 | ... P8: ='Historical FS'!P32 -> 0.15646291
B9: Return on Asset | C9: ='Historical FS'!C31/'Historical FS'!C53 -> 0.24729403 | D9: ='Historical FS'!D31/'Historical FS'!D53 -> 0.27286978 | E9: ='Historical FS'!E31/'Historical FS'!E53 -> 0.30801439 | F9: ='Historical FS'!F31/'Historical FS'!F53 -> 0.3141964 | G9: ='Historical FS'!G31/'Historical FS'!G53 -> 0.11389293 | H9: ='Historical FS'!H31/'Historical FS'!H53 -> 0.12301081 | I9: ='Historical FS'!I31/'Historical FS'!I53 -> 0.13266828 | J9: ='Historical FS'!J31/'Historical FS'!J53 -> 0.12059015 | ... P9: ='Historical FS'!P31/'Historical FS'!P53 -> 0.10453484
B10: Return on Equity | C10: ='Historical FS'!C31/SUM('Historical FS'!C35:C36) -> 0.57591934 | D10: ='Historical FS'!D31/SUM('Historical FS'!D35:D36) -> 0.66941354 | E10: ='Historical FS'!E31/SUM('Historical FS'!E35:E36) -> 0.72937587 | F10: ='Historical FS'!F31/SUM('Historical FS'!F35:F36) -> 0.76947381 | G10: ='Historical FS'!G31/SUM('Historical FS'!G35:G36) -> 0.16421949 | H10: ='Historical FS'!H31/SUM('Historical FS'!H35:H36) -> 0.17677993 | I10: ='Historical FS'!I31/SUM('Historical FS'!I35:I36) -> 0.19272821 | J10: ='Historical FS'!J31/SUM('Historical FS'!J35:J36) -> 0.18479831 | ... P10: ='Historical FS'!P31/SUM('Historical FS'!P35:P36) -> 0.16031727
B12: Solvency Ratios
B13: D/E Ratio | C13: ='Historical FS'!C37/SUM('Historical FS'!C35:C36) -> 0.041073547 | D13: ='Historical FS'!D37/SUM('Historical FS'!D35:D36) -> 0 | E13: ='Historical FS'!E37/SUM('Historical FS'!E35:E36) -> 0.012584213 | F13: ='Historical FS'!F37/SUM('Historical FS'!F35:F36) -> 0 | G13: ='Historical FS'!G37/SUM('Historical FS'!G35:G36) -> 0 | H13: ='Historical FS'!H37/SUM('Historical FS'!H35:H36) -> 0.021259249 | I13: ='Historical FS'!I37/SUM('Historical FS'!I35:I36) -> 0.024232665 | J13: ='Historical FS'!J37/SUM('Historical FS'!J35:J36) -> 0.028974189 | ... P13: ='Historical FS'!P37/SUM('Historical FS'!P35:P36) -> 0.033634908
B14: Debt Ratio | C14: ='Historical FS'!C37/'Historical FS'!C53 -> 0.017636572 | D14: ='Historical FS'!D37/'Historical FS'!D53 -> 0 | E14: ='Historical FS'!E37/'Historical FS'!E53 -> 0.0053142949 | F14: ='Historical FS'!F37/'Historical FS'!F53 -> 0 | G14: ='Historical FS'!G37/'Historical FS'!G53 -> 0 | H14: ='Historical FS'!H37/'Historical FS'!H53 -> 0.014793067 | I14: ='Historical FS'!I37/'Historical FS'!I53 -> 0.016681035 | J14: ='Historical FS'!J37/'Historical FS'!J53 -> 0.018907108 | ... P14: ='Historical FS'!P37/'Historical FS'!P53 -> 0.021931635
B15: Interest Coverage | C15: ='Historical FS'!C21/'Historical FS'!C24 -> 168.45714 | D15: ='Historical FS'!D21/'Historical FS'!D24 -> 268.42308 | E15: ='Historical FS'!E21/'Historical FS'!E24 -> 251.9697 | F15: ='Historical FS'!F21/'Historical FS'!F24 -> 75.076271 | G15: ='Historical FS'!G21/'Historical FS'!G24 -> 90.188034 | H15: ='Historical FS'!H21/'Historical FS'!H24 -> 111 | I15: ='Historical FS'!I21/'Historical FS'!I24 -> 114.12281 | J15: ='Historical FS'!J21/'Historical FS'!J24 -> 40.248503 | ... P15: ='Historical FS'!P21/'Historical FS'!P24 -> 30.329213
B17: Efficiency Ratios
B18: Asset Turnover | C18: ='Historical FS'!C6/'Historical FS'!C53 -> 2.1114224 | D18: ='Historical FS'!D6/'Historical FS'!D53 -> 1.9899787 | E18: ='Historical FS'!E6/'Historical FS'!E53 -> 2.1101508 | F18: ='Historical FS'!F6/'Historical FS'!F53 -> 1.9740485 | G18: ='Historical FS'!G6/'Historical FS'!G53 -> 0.68414315 | H18: ='Historical FS'!H6/'Historical FS'!H53 -> 0.74385159 | I18: ='Historical FS'!I6/'Historical FS'!I53 -> 0.8289886 | J18: ='Historical FS'!J6/'Historical FS'!J53 -> 0.78859458 | ... P18: ='Historical FS'!P6/'Historical FS'!P53 -> 0.6681126
B19: Inventory Turnover | C19: ='Historical FS'!C9/'Historical FS'!C49 -> 7.3494687 | D19: ='Historical FS'!D9/'Historical FS'!D49 -> 7.6856347 | E19: ='Historical FS'!E9/'Historical FS'!E49 -> 8.1899767 | F19: ='Historical FS'!F9/'Historical FS'!F49 -> 7.4499458 | G19: ='Historical FS'!G9/'Historical FS'!G49 -> 7.0692931 | H19: ='Historical FS'!H9/'Historical FS'!H49 -> 7.0961914 | I19: ='Historical FS'!I9/'Historical FS'!I49 -> 8.3229828 | J19: ='Historical FS'!J9/'Historical FS'!J49 -> 8.366733 | ... P19: ='Historical FS'!P9/'Historical FS'!P49 -> 7.8097957
B20: Receivable Turnover | C20: ='Historical FS'!C6/'Historical FS'!C48 -> 30.564055 | D20: ='Historical FS'!D6/'Historical FS'!D48 -> 27.133588 | E20: ='Historical FS'!E6/'Historical FS'!E48 -> 21.646476 | F20: ='Historical FS'!F6/'Historical FS'!F48 -> 34.624021 | G20: ='Historical FS'!G6/'Historical FS'!G48 -> 26.750853 | H20: ='Historical FS'!H6/'Historical FS'!H48 -> 23.455277 | I20: ='Historical FS'!I6/'Historical FS'!I48 -> 19.675219 | J20: ='Historical FS'!J6/'Historical FS'!J48 -> 20.652653 | ... P20: ='Historical FS'!P6/'Historical FS'!P48 -> 16.416646
B21: Payable Turnover | C21: ='Historical FS'!C6/'Historical FS'!C39 -> 5.3608147 | D21: ='Historical FS'!D6/'Historical FS'!D39 -> 4.9574616 | E21: ='Historical FS'!E6/'Historical FS'!E39 -> 5.4551762 | F21: ='Historical FS'!F6/'Historical FS'!F39 -> 5.2797611 | G21: ='Historical FS'!G6/'Historical FS'!G39 -> 5.3428766 | H21: ='Historical FS'!H6/'Historical FS'!H39 -> 5.7836348 | I21: ='Historical FS'!I6/'Historical FS'!I39 -> 6.3275538 | J21: ='Historical FS'!J6/'Historical FS'!J39 -> 5.9027274 | ... P21: ='Historical FS'!P6/'Historical FS'!P39 -> 5.442483
B22: Fixed Asset Turnover | C22: ='Historical FS'!C6/'Historical FS'!C43 -> 7.5044128 | D22: ='Historical FS'!D6/'Historical FS'!D43 -> 7.8500442 | E22: ='Historical FS'!E6/'Historical FS'!E43 -> 8.3372216 | F22: ='Historical FS'!F6/'Historical FS'!F43 -> 7.2609965 | G22: ='Historical FS'!G6/'Historical FS'!G43 -> 0.91417686 | H22: ='Historical FS'!H6/'Historical FS'!H43 -> 1.0189031 | I22: ='Historical FS'!I6/'Historical FS'!I43 -> 1.1500057 | J22: ='Historical FS'!J6/'Historical FS'!J43 -> 1.151682 | ... P22: ='Historical FS'!P6/'Historical FS'!P43 -> 0.89294409
B24: Liquidity Ratios
B25: Current Ratio | C25: ='Historical FS'!C51/SUM('Historical FS'!C37,'Historical FS'!C39) -> 0.84388055 | D25: ='Historical FS'!D51/SUM('Historical FS'!D37,'Historical FS'!D39) -> 1.0192469 | E25: ='Historical FS'!E51/SUM('Historical FS'!E37,'Historical FS'!E39) -> 1.1152635 | F25: ='Historical FS'!F51/SUM('Historical FS'!F37,'Historical FS'!F39) -> 1.1982747 | G25: ='Historical FS'!G51/SUM('Historical FS'!G37,'Historical FS'!G39) -> 1.1142922 | H25: ='Historical FS'!H51/SUM('Historical FS'!H37,'Historical FS'!H39) -> 1.0066264 | I25: ='Historical FS'!I51/SUM('Historical FS'!I37,'Historical FS'!I39) -> 1.112573 | J25: ='Historical FS'!J51/SUM('Historical FS'!J37,'Historical FS'!J39) -> 1.217878 | ... P25: ='Historical FS'!P51/SUM('Historical FS'!P37,'Historical FS'!P39) -> 0.98738228
B26: Quick Ratio | C26: =('Historical FS'!C51-'Historical FS'!C49)/SUM('Historical FS'!C39,'Historical FS'!C37) -> 0.45071948 | D26: =('Historical FS'!D51-'Historical FS'!D49)/SUM('Historical FS'!D39,'Historical FS'!D37) -> 0.66875872 | E26: =('Historical FS'!E51-'Historical FS'!E49)/SUM('Historical FS'!E39,'Historical FS'!E37) -> 0.76290212 | F26: =('Historical FS'!F51-'Historical FS'!F49)/SUM('Historical FS'!F39,'Historical FS'!F37) -> 0.83105508 | G26: =('Historical FS'!G51-'Historical FS'!G49)/SUM('Historical FS'!G39,'Historical FS'!G37) -> 0.70768007 | H26: =('Historical FS'!H51-'Historical FS'!H49)/SUM('Historical FS'!H39,'Historical FS'!H37) -> 0.60152309 | I26: =('Historical FS'!I51-'Historical FS'!I49)/SUM('Historical FS'!I39,'Historical FS'!I37) -> 0.71870657 | J26: =('Historical FS'!J51-'Historical FS'!J49)/SUM('Historical FS'!J39,'Historical FS'!J37) -> 0.88187135 | ... P26: =('Historical FS'!P51-'Historical FS'!P49)/SUM('Historical FS'!P39,'Historical FS'!P37) -> 0.6602387
B27: Cash Ratio | C27: ='Historical FS'!C50/SUM('Historical FS'!C39,'Historical FS'!C37) -> 0.28284079 | D27: ='Historical FS'!D50/SUM('Historical FS'!D39,'Historical FS'!D37) -> 0.486053 | E27: ='Historical FS'!E50/SUM('Historical FS'!E39,'Historical FS'!E37) -> 0.51430527 | F27: ='Historical FS'!F50/SUM('Historical FS'!F39,'Historical FS'!F37) -> 0.67856669 | G27: ='Historical FS'!G50/SUM('Historical FS'!G39,'Historical FS'!G37) -> 0.50795274 | H27: ='Historical FS'!H50/SUM('Historical FS'!H39,'Historical FS'!H37) -> 0.38037781 | I27: ='Historical FS'!I50/SUM('Historical FS'!I39,'Historical FS'!I37) -> 0.43342907 | J27: ='Historical FS'!J50/SUM('Historical FS'!J39,'Historical FS'!J37) -> 0.63149541 | ... P27: ='Historical FS'!P50/SUM('Historical FS'!P39,'Historical FS'!P37) -> 0.37896737
B29: Market Ratios
B30: Earning per share | C30: ='Historical FS'!C6/'Data Sheet'!B124 -> 153.22275 | D30: ='Historical FS'!D6/'Data Sheet'!C124 -> 164.21806 | E30: ='Historical FS'!E6/'Data Sheet'!D124 -> 181.5956 | F30: ='Historical FS'!F6/'Data Sheet'!E124 -> 183.77217 | G30: ='Historical FS'!G6/'Data Sheet'!F124 -> 200.15322 | H30: ='Historical FS'!H6/'Data Sheet'!G124 -> 223.21246 | I30: ='Historical FS'!I6/'Data Sheet'!H124 -> 257.83112 | J30: ='Historical FS'!J6/'Data Sheet'!I124 -> 263.43207 | ... L30: ='Historical FS'!L6/'Data Sheet'!K124 -> 274.37862 | M30: =FORECAST(M$3,C30:L30,C$3:L$3) -> 299.5555 | N30: =FORECAST(N$3,D30:M30,D$3:M$3) -> 315.53373 | O30: =FORECAST(O$3,E30:N30,E$3:N$3) -> 331.08567 | P30: =FORECAST(P$3,F30:O30,F$3:O$3) -> 347.41062
B31: P/E Ratio | C31: ='Data Sheet'!B121/'Ratio Analysis'!C30 -> 5.695042 | D31: ='Data Sheet'!C121/'Ratio Analysis'!D30 -> 7.770826 | E31: ='Data Sheet'!D121/'Ratio Analysis'!E30 -> 8.9954271 | F31: ='Data Sheet'!E121/'Ratio Analysis'!F30 -> 11.970419 | G31: ='Data Sheet'!F121/'Ratio Analysis'!G30 -> 11.626693 | H31: ='Data Sheet'!G121/'Ratio Analysis'!H30 -> 8.7840078 | I31: ='Data Sheet'!H121/'Ratio Analysis'!I30 -> 9.5040506 | J31: ='Data Sheet'!I121/'Ratio Analysis'!J30 -> 8.2265609 | ... L31: ='Data Sheet'!K121/'Ratio Analysis'!L30 -> 7.4903796 | M31: =FORECAST(M$3,C31:L31,C$3:L$3) -> 8.9447722 | N31: =FORECAST(N$3,D31:M31,D$3:M$3) -> 8.1676671 | O31: =FORECAST(O$3,E31:N31,E$3:N$3) -> 7.4163617 | P31: =FORECAST(P$3,F31:O31,F$3:O$3) -> 6.6642982
B32: Book Value per share | C32: =SUM('Historical FS'!C35:C36)/'Data Sheet'!B124 -> 31.16019 | D32: =SUM('Historical FS'!D35:D36)/'Data Sheet'!C124 -> 33.638254 | E32: =SUM('Historical FS'!E35:E36)/'Data Sheet'!D124 -> 36.342218 | F32: =SUM('Historical FS'!F35:F36)/'Data Sheet'!E124 -> 38.012749 | G32: =SUM('Historical FS'!G35:G36)/'Data Sheet'!F124 -> 202.90262 | H32: =SUM('Historical FS'!H35:H36)/'Data Sheet'!G124 -> 208.80575 | I32: =SUM('Historical FS'!I35:I36)/'Data Sheet'!H124 -> 214.09602 | J32: =SUM('Historical FS'!J35:J36)/'Data Sheet'!I124 -> 217.98604 | ... L32: =SUM('Historical FS'!L35:L36)/'Data Sheet'!K124 -> 207.43531 | M32: =FORECAST(M$3,C32:L32,C$3:L$3) -> 282.20645 | N32: =FORECAST(N$3,D32:M32,D$3:M$3) -> 310.01233 | O32: =FORECAST(O$3,E32:N32,E$3:N$3) -> 332.87593 | P32: =FORECAST(P$3,F32:O32,F$3:O$3) -> 347.1867
B34: Operating Cycle Ratios
B35: (in days)
B36: Inventory Days | C36: =365/C19 -> 49.663454 | D36: =365/D19 -> 47.491198 | E36: =365/E19 -> 44.566671 | F36: =365/F19 -> 48.993645 | G36: =365/G19 -> 51.631754 | H36: =365/H19 -> 51.436042 | I36: =365/I19 -> 43.85447 | J36: =365/J19 -> 43.625152 | ... P36: =365/P19 -> 46.736178
B37: Receivable Days | C37: =365/C20 -> 11.942133 | D37: =365/D20 -> 13.451962 | E37: =365/E20 -> 16.861867 | F37: =365/F20 -> 10.541814 | G37: =365/G20 -> 13.644425 | H37: =365/H20 -> 15.56153 | I37: =365/I20 -> 18.551255 | J37: =365/J20 -> 17.673275 | ... P37: =365/P20 -> 22.233531
B38: Payable Days | C38: =365/C21 -> 68.086665 | D38: =365/D21 -> 73.626389 | E38: =365/E21 -> 66.908929 | F38: =365/F21 -> 69.131916 | G38: =365/G21 -> 68.315259 | H38: =365/H21 -> 63.109103 | I38: =365/I21 -> 57.684219 | J38: =365/J21 -> 61.835821 | ... P38: =365/P21 -> 67.064978
B40: Cash Conversion Cycle | C40: =SUM(C36:C37)-C38 -> -6.4810791 | D40: =SUM(D36:D37)-D38 -> -12.683229 | E40: =SUM(E36:E37)-E38 -> -5.4803904 | F40: =SUM(F36:F37)-F38 -> -9.5964562 | G40: =SUM(G36:G37)-G38 -> -3.0390807 | H40: =SUM(H36:H37)-H38 -> 3.8884694 | I40: =SUM(I36:I37)-I38 -> 4.7215052 | J40: =SUM(J36:J37)-J38 -> -0.53739455 | ... P40: =SUM(P36:P37)-P38 -> 1.9047315

Sheet DCF Modelling
B2: ="WACC Calculation for "&'Data Sheet'!B1 -> WACC Calculation for HINDUSTAN UNILEVER LTD | E2: ="Discounted Cash Flow Statement for "&'Data Sheet'!B1 -> Discounted Cash Flow Statement for HINDUSTAN UNILEVER LTD
F3: 1 | G3: 2 | H3: 3 | I3: 4 | J3: 5 | K3: 6 | L3: 7 | M3: 8 | N3: 9 | O3: 10
B4: Equity (E) | C4: ='Data Sheet'!B9/100 -> 5166.8609
B5: Debt (D) | C5: 1478 | E5: EBIT | F5: ='Historical FS'!C21 -> 5896 | G5: ='Historical FS'!D21 -> 6979 | H5: ='Historical FS'!E21 -> 8315 | I5: ='Historical FS'!F21 -> 8859 | J5: ='Historical FS'!G21 -> 10552 | K5: ='Historical FS'!H21 -> 11766 | L5: ='Historical FS'!I21 -> 13010 | M5: ='Historical FS'!J21 -> 13443 | ... O5: ='Historical FS'!L21 -> 13706
B6: Rf | C6: 0.0702 | E6: Tax Rate | F6: =$C$10 -> 0.23766546 | G6: =$C$10 -> 0.23766546 | H6: =$C$10 -> 0.23766546 | I6: =$C$10 -> 0.23766546 | J6: =$C$10 -> 0.23766546 | K6: =$C$10 -> 0.23766546 | L6: =$C$10 -> 0.23766546 | M6: =$C$10 -> 0.23766546 | ... O6: =$C$10 -> 0.23766546
B7: Equity Risk Premium (ERP) | C7: 0.0418 | E7: Depreciation | F7: ='Historical FS'!C19 -> 432 | G7: ='Historical FS'!D19 -> 520 | H7: ='Historical FS'!E19 -> 565 | I7: ='Historical FS'!F19 -> 1002 | J7: ='Historical FS'!G19 -> 1074 | K7: ='Historical FS'!H19 -> 1091 | L7: ='Historical FS'!I19 -> 1137 | M7: ='Historical FS'!J19 -> 1216 | ... O7: ='Historical FS'!L19 -> 1333
B8: Rm | C8: =C6+(C9*C7) -> 0.102386 | E8: CapEx | F8: ='Historical FS'!C74 -> -1113 | G8: ='Historical FS'!D74 -> -895 | H8: ='Historical FS'!E74 -> -767 | I8: ='Historical FS'!F74 -> -862 | J8: ='Historical FS'!G74 -> -4613 | K8: ='Historical FS'!H74 -> -1228 | L8: ='Historical FS'!I74 -> -1192 | M8: ='Historical FS'!J74 -> -1477 | ... O8: ='Historical FS'!L74 -> -1360
B9: Beta | C9: 0.77 | E9: Non-Cash WC | F9: ='Historical FS'!C48+'Historical FS'!C49-'Historical FS'!C39 -> -2560 | G9: ='Historical FS'!D48+'Historical FS'!D49-'Historical FS'!D39 -> -3347 | H9: ='Historical FS'!E48+'Historical FS'!E49-'Historical FS'!E39 -> -2816 | I9: ='Historical FS'!F48+'Historical FS'!F49-'Historical FS'!F39 -> -3619 | J9: ='Historical FS'!G48+'Historical FS'!G49-'Historical FS'!G39 -> -3465 | K9: ='Historical FS'!H48+'Historical FS'!H49-'Historical FS'!H39 -> -2736 | L9: ='Historical FS'!I48+'Historical FS'!I49-'Historical FS'!I39 -> -2244 | M9: ='Historical FS'!J48+'Historical FS'!J49-'Historical FS'!J39 -> -3467 | ... O9: ='Historical FS'!L48+'Historical FS'!L49-'Historical FS'!L39 -> -5157
B10: Tax Rate | C10: ='Historical FS'!L29/'Historical FS'!L26 -> 0.23766546 | E10: FCF | F10: =F5*(1-F6)+F7+F8+F9 -> 1253.7244 | G10: =G5*(1-G6)+G7+G8+G9 -> 1598.3327 | H10: =H5*(1-H6)+H7+H8+H9 -> 3320.8117 | I10: =I5*(1-I6)+I7+I8+I9 -> 3274.5217 | J10: =J5*(1-J6)+J7+J8+J9 -> 1040.154 | K10: =K5*(1-K6)+K7+K8+K9 -> 6096.6282 | L10: =L5*(1-L6)+L7+L8+L9 -> 7618.9723 | M10: =M5*(1-M6)+M7+M8+M9 -> 6520.0632 | ... O10: =O5*(1-O6)+O7+O8+O9 -> 5264.5572
B11: Cost of Debt (Kd) | C11: =(('Historical FS'!L78+'Historical FS'!L89)/'DCF Modelling'!C5)*(1-C10) -> 0.15215743
E12: Growth Rate | F12: 0.038
B13: Cost of Equity (Ke) | C13: =C6+(C8-C6)*C9 -> 0.09498322 | E13: WACC | F13: =C17 -> 0.099656789
B14: ew | C14: =C4/SUM(C4:C5) -> 0.77757247 | E14: Terminal Value | F14: =(O10*(1+F12))/(F13-F12) -> 88629.499
B15: dw | C15: =C5/SUM(C4:C5) -> 0.22242753
E16: Discount Factor | F16: =1/((1+$F$13)^F3) -> 0.90937464 | G16: =1/((1+$F$13)^G3) -> 0.82696224 | H16: =1/((1+$F$13)^H3) -> 0.75201849 | I16: =1/((1+$F$13)^I3) -> 0.68386655 | J16: =1/((1+$F$13)^J3) -> 0.6218909 | K16: =1/((1+$F$13)^K3) -> 0.56553181 | L16: =1/((1+$F$13)^L3) -> 0.51428029 | M16: =1/((1+$F$13)^M3) -> 0.46767346 | ... O16: =1/((1+$F$13)^O3) -> 0.38674829
B17: WACC | C17: =(C14*C13)+(C15*C11*(1-C10)) -> 0.099656789 | E17: PV of FCF | F17: =F10*F16 -> 1140.1052 | G17: =G10*G16 -> 1321.7608 | H17: =H10*H16 -> 2497.3118 | I17: =I10*I16 -> 2239.3358 | J17: =J10*J16 -> 646.86233 | K17: =K10*K16 -> 3447.8372 | L17: =L10*L16 -> 3918.2873 | M17: =M10*M16 -> 3049.2605 | ... O17: =O10*O16 -> 2036.0585
E18: PV of TV | O18: =F14*O16 -> 34277.307
E20: Enterprise Value | F20: =SUM(F17:O18) -> 57670.823
E21: Equity Value | F21: =F20-('Historical FS'!C37-'Historical FS'!C50) -> 59221.823
E23: No. Shares | F23: ='Data Sheet'!K124/10 -> 23.496
E24: Share Price | F24: =F21/F23 -> 2520.5066

Sheet COMP Analysis
B2: ="COMP Analysis for "&'Data Sheet'!B1 -> COMP Analysis for HINDUSTAN UNILEVER LTD
C3: Market Data | I3: Financials | N3: Valuation
B4: Name | C4: Share Price | D4: Share Outstanding | E4: Market Cap | F4: Net Debt | G4: Enterprise Value | I4: Revenue | J4: EBITDA | K4: EBIT | L4: Net Income | N4: EV/Revenue | O4: Ev/EBITDA | P4: P/E (Calculated) | Q4: P/E (Actual)
B5: HUL | C5: 2203 | D5: 234.96 | E5: =C5*D5 -> 517616.88 | F5: ='Historical FS'!L37-'Historical FS'!L50 -> -1770 | G5: =SUM(E5:F5) -> 515846.88 | I5: ='Historical FS'!L6 -> 64468 | J5: ='Historical FS'!L16 -> 15039 | K5: ='Historical FS'!L21 -> 13706 | L5: ='Historical FS'!L31 -> 10136 | N5: =G5/I5 -> 8.0015958 | O5: =G5/J5 -> 34.30061 | P5: 47.26 | Q5: =E5/L5 -> 51.067174
B6: ITC | C6: 301.5 | D6: 1252.95 | E6: =C6*D6 -> 377764.42 | F6: =2399-3009 -> -610 | G6: =SUM(E6:F6) -> 377154.42 | I6: 78868 | J6: =28033+85+1711 -> 29829 | K6: =J6-1711 -> 28118 | L6: 21018 | N6: =G6/I6 -> 4.782097 | O6: =G6/J6 -> 12.643884 | P6: 17.49 | Q6: =E6/L6 -> 17.973376
B7: Hindustan Foofs | C7: 536.2 | D7: 12.12 | E7: =C7*D7 -> 6498.744 | F7: =1088-52 -> 1036 | G7: =SUM(E7:F7) -> 7534.744 | I7: 4251 | J7: =200+82+90 -> 372 | K7: =J7-90 -> 282 | L7: 149 | N7: =G7/I7 -> 1.7724639 | O7: =G7/J7 -> 20.254688 | P7: 42.5 | Q7: =E7/L7 -> 43.615732
B8: Godavri Bioref. | C8: 283.75 | D8: 5.12 | E8: =C8*D8 -> 1452.8 | F8: =531-32 -> 499 | G8: =SUM(E8:F8) -> 1951.8 | I8: 1988 | J8: =5+49+54 -> 108 | K8: =J8-54 -> 54 | L8: 4 | N8: =G8/I8 -> 0.98179074 | O8: =G8/J8 -> 18.072222 | P8: 43.03 | Q8: =E8/L8 -> 363.2
B11: High | N11: =MAX(N5:N8) -> 8.0015958 | O11: =MAX(O5:O8) -> 34.30061 | P11: =MAX(P5:P8) -> 47.26 | Q11: =MAX(Q5:Q8) -> 363.2
B12: Third Quratile | N12: =QUARTILE(N5:N8,3) -> 5.5869717 | O12: =QUARTILE(O5:O8,3) -> 23.766169 | P12: =QUARTILE(P5:P8,3) -> 44.0875 | Q12: =QUARTILE(Q5:Q8,3) -> 129.10038
B13: Median | N13: =MEDIAN(N5:N8) -> 3.2772804 | O13: =MEDIAN(O5:O8) -> 19.163455 | P13: =MEDIAN(P5:P8) -> 42.765 | Q13: =MEDIAN(Q5:Q8) -> 47.341453
B14: Average | N14: =AVERAGE(N5:N8) -> 3.8844869 | O14: =AVERAGE(O5:O8) -> 21.317851 | P14: =AVERAGE(P5:P8) -> 37.57 | Q14: =AVERAGE(Q5:Q8) -> 118.96407
B15: First Quartile | N15: =QUARTILE(N5:N8,1) -> 1.5747956 | O15: =QUARTILE(O5:O8,1) -> 16.715138 | P15: =QUARTILE(P5:P8,1) -> 36.2475 | Q15: =QUARTILE(Q5:Q8,1) -> 37.205143
B16: Low | N16: =MIN(N5:N8) -> 0.98179074 | O16: =MIN(O5:O8) -> 12.643884 | P16: =MIN(P5:P8) -> 17.49 | Q16: =MIN(Q5:Q8) -> 17.973376
B18: HUL
B19: Implied Enterprise Value | N19: =$G$5*N13 -> 1690574.9 | O19: =$G$5*O13 -> 9885408.6 | P19: =$G$5*P13 -> 22060192 | Q19: =$G$5*Q13 -> 24420941
B20: Net Debt | N20: =$F$5 -> -1770 | O20: =$F$5 -> -1770 | P20: =$F$5 -> -1770 | Q20: =$F$5 -> -1770
B21: Implied Market Value | N21: =N19+N20 -> 1688804.9 | O21: =O19+O20 -> 9883638.6 | P21: =P19+P20 -> 22058422 | Q21: =Q19+Q20 -> 24419171
B22: Shares Outstanding | N22: =$D$5 -> 234.96 | O22: =$D$5 -> 234.96 | P22: =$D$5 -> 234.96 | Q22: =$D$5 -> 234.96
B23: Implied Value per Share | N23: =N21/N22 -> 7187.6272 | O23: =O21/O22 -> 42065.197 | P23: =P21/P22 -> 93881.605 | Q23: =Q21/Q22 -> 103929.06

Sheet Common Size Statement
B2: ="Common Size Income Statement for "&'Data Sheet'!$B$1 -> Common Size Income Statement for HINDUSTAN UNILEVER LTD
B3: Year | C3: ='Data Sheet'!B$16 -> 42825 | D3: ='Data Sheet'!C$16 -> 43190 | E3: ='Data Sheet'!D$16 -> 43555 | F3: ='Data Sheet'!E$16 -> 43921 | G3: ='Data Sheet'!F$16 -> 44286 | H3: ='Data Sheet'!G$16 -> 44651 | I3: ='Data Sheet'!H$16 -> 45016 | J3: ='Data Sheet'!I$16 -> 45382 | ... L3: ='Data Sheet'!K$16 -> 46112
B4: ='Data Sheet'!A17 -> Sales | C4: ='Data Sheet'!B17/'Data Sheet'!B$17 -> 1 | D4: ='Data Sheet'!C17/'Data Sheet'!C$17 -> 1 | E4: ='Data Sheet'!D17/'Data Sheet'!D$17 -> 1 | F4: ='Data Sheet'!E17/'Data Sheet'!E$17 -> 1 | G4: ='Data Sheet'!F17/'Data Sheet'!F$17 -> 1 | H4: ='Data Sheet'!G17/'Data Sheet'!G$17 -> 1 | I4: ='Data Sheet'!H17/'Data Sheet'!H$17 -> 1 | J4: ='Data Sheet'!I17/'Data Sheet'!I$17 -> 1 | ... L4: ='Data Sheet'!K17/'Data Sheet'!K$17 -> 1
B5: ='Data Sheet'!A18 -> Raw Material Cost | C5: ='Data Sheet'!B18/'Data Sheet'!B$17 -> 0.41028888 | D5: ='Data Sheet'!C18/'Data Sheet'!C$17 -> 0.400422 | E5: ='Data Sheet'!D18/'Data Sheet'!D$17 -> 0.4030781 | F5: ='Data Sheet'!E18/'Data Sheet'!E$17 -> 0.39456552 | G5: ='Data Sheet'!F18/'Data Sheet'!F$17 -> 0.42827677 | H5: ='Data Sheet'!G18/'Data Sheet'!G$17 -> 0.43608664 | I5: ='Data Sheet'!H18/'Data Sheet'!H$17 -> 0.46924728 | J5: ='Data Sheet'!I18/'Data Sheet'!I$17 -> 0.4333398 | ... L5: ='Data Sheet'!K18/'Data Sheet'!K$17 -> 0.49782838
B6: ='Data Sheet'!A19 -> Change in Inventory | C6: ='Data Sheet'!B19/'Data Sheet'!B$17 -> -0.0043423195 | D6: ='Data Sheet'!C19/'Data Sheet'!C$17 -> 0.0020256014 | E6: ='Data Sheet'!D19/'Data Sheet'!D$17 -> -0.00030526584 | F6: ='Data Sheet'!E19/'Data Sheet'!E$17 -> 0.0027147274 | G6: ='Data Sheet'!F19/'Data Sheet'!F$17 -> 0.0086118908 | H6: ='Data Sheet'!G19/'Data Sheet'!G$17 -> 0.00041947908 | I6: ='Data Sheet'!H19/'Data Sheet'!H$17 -> 0.0012380324 | J6: ='Data Sheet'!I19/'Data Sheet'!I$17 -> 0.00017771746 | ... L6: ='Data Sheet'!K19/'Data Sheet'!K$17 -> 0.0066544642
B7: ='Data Sheet'!A20 -> Power and Fuel | C7: ='Data Sheet'!B20/'Data Sheet'!B$17 -> 0.008895724 | D7: ='Data Sheet'!C20/'Data Sheet'!C$17 -> 0.0082993389 | E7: ='Data Sheet'!D20/'Data Sheet'!D$17 -> 0.0078351564 | F7: ='Data Sheet'!E20/'Data Sheet'!E$17 -> 0.0075157731 | G7: ='Data Sheet'!F20/'Data Sheet'!F$17 -> 0.0072084715 | H7: ='Data Sheet'!G20/'Data Sheet'!G$17 -> 0.0060633795 | I7: ='Data Sheet'!H20/'Data Sheet'!H$17 -> 0.0063387257 | J7: ='Data Sheet'!I20/'Data Sheet'!I$17 -> 0.0072056353 | ... L7: ='Data Sheet'!K20/'Data Sheet'!K$17 -> 0
B8: ='Data Sheet'!A21 -> Other Mfr. Exp | C8: ='Data Sheet'!B21/'Data Sheet'!B$17 -> 0.087057475 | D8: ='Data Sheet'!C21/'Data Sheet'!C$17 -> 0.08434379 | E8: ='Data Sheet'!D21/'Data Sheet'!D$17 -> 0.077359451 | F8: ='Data Sheet'!E21/'Data Sheet'!E$17 -> 0.073046276 | G8: ='Data Sheet'!F21/'Data Sheet'!F$17 -> 0.060984945 | H8: ='Data Sheet'!G21/'Data Sheet'!G$17 -> 0.063951493 | I8: ='Data Sheet'!H21/'Data Sheet'!H$17 -> 0.062578409 | J8: ='Data Sheet'!I21/'Data Sheet'!I$17 -> 0.05468851 | ... L8: ='Data Sheet'!K21/'Data Sheet'!K$17 -> 0
B9: ='Data Sheet'!A22 -> Employee Cost | C9: ='Data Sheet'!B22/'Data Sheet'!B$17 -> 0.052560159 | D9: ='Data Sheet'!C22/'Data Sheet'!C$17 -> 0.052328035 | E9: ='Data Sheet'!D22/'Data Sheet'!D$17 -> 0.047697787 | F9: ='Data Sheet'!E22/'Data Sheet'!E$17 -> 0.045748184 | G9: ='Data Sheet'!F22/'Data Sheet'!F$17 -> 0.050140342 | H9: ='Data Sheet'!G22/'Data Sheet'!G$17 -> 0.048526103 | I9: ='Data Sheet'!H22/'Data Sheet'!H$17 -> 0.047111258 | J9: ='Data Sheet'!I22/'Data Sheet'!I$17 -> 0.048613804 | ... L9: ='Data Sheet'!K22/'Data Sheet'!K$17 -> 0.04924924
B10: ='Data Sheet'!A23 -> Selling and admin | C10: ='Data Sheet'!B23/'Data Sheet'!B$17 -> 0.20170677 | D10: ='Data Sheet'!C23/'Data Sheet'!C$17 -> 0.20402307 | E10: ='Data Sheet'!D23/'Data Sheet'!D$17 -> 0.19832104 | F10: ='Data Sheet'!E23/'Data Sheet'!E$17 -> 0.1915391 | G10: ='Data Sheet'!F23/'Data Sheet'!F$17 -> 0.16811261 | H10: ='Data Sheet'!G23/'Data Sheet'!G$17 -> 0.15566487 | I10: ='Data Sheet'!H23/'Data Sheet'!H$17 -> 0.14501486 | J10: ='Data Sheet'!I23/'Data Sheet'!I$17 -> 0.17416311 | ... L10: ='Data Sheet'!K23/'Data Sheet'!K$17 -> 0.09711795
B11: ='Data Sheet'!A24 -> Other Expenses | C11: ='Data Sheet'!B24/'Data Sheet'!B$17 -> 0.044327845 | D11: ='Data Sheet'!C24/'Data Sheet'!C$17 -> 0.041637361 | E11: ='Data Sheet'!D24/'Data Sheet'!D$17 -> 0.039506487 | F11: ='Data Sheet'!E24/'Data Sheet'!E$17 -> 0.042430184 | G11: ='Data Sheet'!F24/'Data Sheet'!F$17 -> 0.046674322 | H11: ='Data Sheet'!G24/'Data Sheet'!G$17 -> 0.044979598 | I11: ='Data Sheet'!H24/'Data Sheet'!H$17 -> 0.037421591 | J11: ='Data Sheet'!I24/'Data Sheet'!I$17 -> 0.045334109 | ... L11: ='Data Sheet'!K24/'Data Sheet'!K$17 -> 0.12918037
B12: ='Data Sheet'!A25 -> Other Income | C12: ='Data Sheet'!B25/'Data Sheet'!B$17 -> 0.018273928 | D12: ='Data Sheet'!C25/'Data Sheet'!C$17 -> 0.0099310733 | E12: ='Data Sheet'!D25/'Data Sheet'!D$17 -> 0.0081912999 | F12: ='Data Sheet'!E25/'Data Sheet'!E$17 -> 0.010657819 | G12: ='Data Sheet'!F25/'Data Sheet'!F$17 -> 0.0036148677 | H12: ='Data Sheet'!G25/'Data Sheet'!G$17 -> 0.0041757236 | I12: ='Data Sheet'!H25/'Data Sheet'!H$17 -> 0.0073951799 | J12: ='Data Sheet'!I25/'Data Sheet'!I$17 -> 0.013199561 | ... L12: ='Data Sheet'!K25/'Data Sheet'!K$17 -> 0.076363467
B13: ='Data Sheet'!A26 -> Depreciation | C13: ='Data Sheet'!B26/'Data Sheet'!B$17 -> 0.013026959 | D13: ='Data Sheet'!C26/'Data Sheet'!C$17 -> 0.014629343 | E13: ='Data Sheet'!D26/'Data Sheet'!D$17 -> 0.014372933 | F13: ='Data Sheet'!E26/'Data Sheet'!E$17 -> 0.025186638 | G13: ='Data Sheet'!F26/'Data Sheet'!F$17 -> 0.022837459 | H13: ='Data Sheet'!G26/'Data Sheet'!G$17 -> 0.020802349 | I13: ='Data Sheet'!H26/'Data Sheet'!H$17 -> 0.01876857 | J13: ='Data Sheet'!I26/'Data Sheet'!I$17 -> 0.019645858 | ... L13: ='Data Sheet'!K26/'Data Sheet'!K$17 -> 0.020676925
B14: ='Data Sheet'!A27 -> Interest | C14: ='Data Sheet'!B27/'Data Sheet'!B$17 -> 0.0010554249 | D14: ='Data Sheet'!C27/'Data Sheet'!C$17 -> 0.00073146715 | E14: ='Data Sheet'!D27/'Data Sheet'!D$17 -> 0.00083948105 | F14: ='Data Sheet'!E27/'Data Sheet'!E$17 -> 0.002966091 | G14: ='Data Sheet'!F27/'Data Sheet'!F$17 -> 0.0024878796 | H14: ='Data Sheet'!G27/'Data Sheet'!G$17 -> 0.0020211265 | I14: ='Data Sheet'!H27/'Data Sheet'!H$17 -> 0.0018818092 | J14: ='Data Sheet'!I27/'Data Sheet'!I$17 -> 0.0053961484 | ... L14: ='Data Sheet'!K27/'Data Sheet'!K$17 -> 0.0063597444
B15: ='Data Sheet'!A28 -> Profit before tax | C15: ='Data Sheet'!B28/'Data Sheet'!B$17 -> 0.19501236 | D15: ='Data Sheet'!C28/'Data Sheet'!C$17 -> 0.20554227 | E15: ='Data Sheet'!D28/'Data Sheet'!D$17 -> 0.2188756 | F15: ='Data Sheet'!E28/'Data Sheet'!E$17 -> 0.23037478 | G15: ='Data Sheet'!F28/'Data Sheet'!F$17 -> 0.22550396 | H15: ='Data Sheet'!G28/'Data Sheet'!G$17 -> 0.22649964 | I15: ='Data Sheet'!H28/'Data Sheet'!H$17 -> 0.22027072 | J15: ='Data Sheet'!I28/'Data Sheet'!I$17 -> 0.22499031 | ... L15: ='Data Sheet'!K28/'Data Sheet'!K$17 -> 0.28260532
... B20: ='Data Sheet'!A33 -> EBIT | C20: ='Data Sheet'!B33/'Data Sheet'!B$17 -> 0.19606779 | D20: ='Data Sheet'!C33/'Data Sheet'!C$17 -> 0.20627374 | E20: ='Data Sheet'!D33/'Data Sheet'!D$17 -> 0.21971509 | F20: ='Data Sheet'!E33/'Data Sheet'!E$17 -> 0.23334087 | G20: ='Data Sheet'!F33/'Data Sheet'!F$17 -> 0.22799183 | H20: ='Data Sheet'!G33/'Data Sheet'!G$17 -> 0.22852076 | I20: ='Data Sheet'!H33/'Data Sheet'!H$17 -> 0.22215253 | J20: ='Data Sheet'!I33/'Data Sheet'!I$17 -> 0.23038645 | ... L20: ='Data Sheet'!K33/'Data Sheet'!K$17 -> 0.28896507
B23: ="Common Size Balance Sheet for "&'Data Sheet'!$B$1 -> Common Size Balance Sheet for HINDUSTAN UNILEVER LTD
B24: Year | C24: ='Data Sheet'!B$16 -> 42825 | D24: ='Data Sheet'!C$16 -> 43190 | E24: ='Data Sheet'!D$16 -> 43555 | F24: ='Data Sheet'!E$16 -> 43921 | G24: ='Data Sheet'!F$16 -> 44286 | H24: ='Data Sheet'!G$16 -> 44651 | I24: ='Data Sheet'!H$16 -> 45016 | J24: ='Data Sheet'!I$16 -> 45382 | ... L24: ='Data Sheet'!K$16 -> 46112
B25: ='Historical FS'!B35 -> Equity Share Capital | C25: ='Historical FS'!C35/'Historical FS'!C$41 -> 0.013752706 | D25: ='Historical FS'!D35/'Historical FS'!D$41 -> 0.012092711 | E25: ='Historical FS'!E35/'Historical FS'!E$41 -> 0.011594825 | F25: ='Historical FS'!F35/'Historical FS'!F$41 -> 0.010718007 | G25: ='Historical FS'!G35/'Historical FS'!G$41 -> 0.0034186791 | H25: ='Historical FS'!H35/'Historical FS'!H$41 -> 0.0033330497 | I25: ='Historical FS'!I35/'Historical FS'!I$41 -> 0.0032157861 | J25: ='Historical FS'!J35/'Historical FS'!J$41 -> 0.0029940501 | ... L25: ='Historical FS'!L35/'Historical FS'!L$41 -> 0.0029466346
B26: ='Historical FS'!B36 -> Reserves | C26: ='Historical FS'!C36/'Historical FS'!C$41 -> 0.41563734 | D26: ='Historical FS'!D36/'Historical FS'!D$41 -> 0.39553242 | E26: ='Historical FS'!E36/'Historical FS'!E$41 -> 0.41070374 | F26: ='Historical FS'!F36/'Historical FS'!F$41 -> 0.3976083 | G26: ='Historical FS'!G36/'Historical FS'!G$41 -> 0.6901222 | H26: ='Historical FS'!H36/'Historical FS'!H$41 -> 0.69250844 | I26: ='Historical FS'!I36/'Historical FS'!I$41 -> 0.68515402 | J26: ='Historical FS'!J36/'Historical FS'!J$41 -> 0.64955599 | ... L26: ='Historical FS'!L36/'Historical FS'!L$41 -> 0.60818537
B27: ='Historical FS'!B37 -> Borrowings | C27: ='Historical FS'!C37/'Historical FS'!C$41 -> 0.017636572 | D27: ='Historical FS'!D37/'Historical FS'!D$41 -> 0 | E27: ='Historical FS'!E37/'Historical FS'!E$41 -> 0.0053142949 | F27: ='Historical FS'!F37/'Historical FS'!F$41 -> 0 | G27: ='Historical FS'!G37/'Historical FS'!G$41 -> 0 | H27: ='Historical FS'!H37/'Historical FS'!H$41 -> 0.014793067 | I27: ='Historical FS'!I37/'Historical FS'!I$41 -> 0.016681035 | J27: ='Historical FS'!J37/'Historical FS'!J$41 -> 0.018907108 | ... L27: ='Historical FS'!L37/'Historical FS'!L$41 -> 0.018532451
B28: ='Historical FS'!B38 -> Other Liabilities | C28: ='Historical FS'!C38/'Historical FS'!C$41 -> 0.15911117 | D28: ='Historical FS'!D38/'Historical FS'!D$41 -> 0.19096406 | E28: ='Historical FS'!E38/'Historical FS'!E$41 -> 0.18557088 | F28: ='Historical FS'!F38/'Historical FS'!F$41 -> 0.21778395 | G28: ='Historical FS'!G38/'Historical FS'!G$41 -> 0.17841141 | H28: ='Historical FS'!H38/'Historical FS'!H$41 -> 0.16075228 | I28: ='Historical FS'!I38/'Historical FS'!I$41 -> 0.16393667 | J28: ='Historical FS'!J38/'Historical FS'!J$41 -> 0.19494451 | ... L28: ='Historical FS'!L38/'Historical FS'!L$41 -> 0.20325509
B29: ='Historical FS'!B39 -> Trade Payables | C29: ='Historical FS'!C39/'Historical FS'!C$41 -> 0.39386222 | D29: ='Historical FS'!D39/'Historical FS'!D$41 -> 0.40141082 | E29: ='Historical FS'!E39/'Historical FS'!E$41 -> 0.38681625 | F29: ='Historical FS'!F39/'Historical FS'!F$41 -> 0.37388974 | G29: ='Historical FS'!G39/'Historical FS'!G$41 -> 0.12804772 | H29: ='Historical FS'!H39/'Historical FS'!H$41 -> 0.12861317 | I29: ='Historical FS'!I39/'Historical FS'!I$41 -> 0.13101249 | J29: ='Historical FS'!J39/'Historical FS'!J$41 -> 0.13359834 | ... L29: ='Historical FS'!L39/'Historical FS'!L$41 -> 0.16708045
B31: ='Historical FS'!B41 -> Total Liabilities | C31: ='Historical FS'!C41/'Historical FS'!C$41 -> 1 | D31: ='Historical FS'!D41/'Historical FS'!D$41 -> 1 | E31: ='Historical FS'!E41/'Historical FS'!E$41 -> 1 | F31: ='Historical FS'!F41/'Historical FS'!F$41 -> 1 | G31: ='Historical FS'!G41/'Historical FS'!G$41 -> 1 | H31: ='Historical FS'!H41/'Historical FS'!H$41 -> 1 | I31: ='Historical FS'!I41/'Historical FS'!I$41 -> 1 | J31: ='Historical FS'!J41/'Historical FS'!J$41 -> 1 | ... L31: ='Historical FS'!L41/'Historical FS'!L$41 -> 1
B33: ='Historical FS'!B43 -> Net Block | C33: ='Historical FS'!C43/'Historical FS'!C$53 -> 0.28135744 | D33: ='Historical FS'!D43/'Historical FS'!D$53 -> 0.25349905 | E33: ='Historical FS'!E43/'Historical FS'!E$53 -> 0.25310001 | F33: ='Historical FS'!F43/'Historical FS'!F$53 -> 0.27187019 | G33: ='Historical FS'!G43/'Historical FS'!G$53 -> 0.74837067 | H33: ='Historical FS'!H43/'Historical FS'!H$53 -> 0.73005134 | I33: ='Historical FS'!I43/'Historical FS'!I$53 -> 0.72085608 | J33: ='Historical FS'!J43/'Historical FS'!J$53 -> 0.68473289 | ... L33: ='Historical FS'!L43/'Historical FS'!L$53 -> 0.72008225
B34: ='Historical FS'!B44 -> Capital Work in Progress | C34: ='Historical FS'!C44/'Historical FS'!C$53 -> 0.014580415 | D34: ='Historical FS'!D44/'Historical FS'!D$53 -> 0.02580898 | E34: ='Historical FS'!E44/'Historical FS'!E$53 -> 0.021793977 | F34: ='Historical FS'!F44/'Historical FS'!F$53 -> 0.029623381 | G34: ='Historical FS'!G44/'Historical FS'!G$53 -> 0.01083794 | H34: ='Historical FS'!H44/'Historical FS'!H$53 -> 0.018622529 | I34: ='Historical FS'!I44/'Historical FS'!I$53 -> 0.01549051 | J34: ='Historical FS'!J44/'Historical FS'!J$53 -> 0.013059155 | ... L34: ='Historical FS'!L44/'Historical FS'!L$53 -> 0.011034206
B35: ='Historical FS'!B45 -> Investments | C35: ='Historical FS'!C45/'Historical FS'!C$53 -> 0.24156373 | D35: ='Historical FS'!D45/'Historical FS'!D$53 -> 0.16084425 | E35: ='Historical FS'!E45/'Historical FS'!E$53 -> 0.14579419 | F35: ='Historical FS'!F45/'Historical FS'!F$53 -> 0.062273607 | G35: ='Historical FS'!G45/'Historical FS'!G$53 -> 0.039409369 | H35: ='Historical FS'!H45/'Historical FS'!H$53 -> 0.049939012 | I35: ='Historical FS'!I45/'Historical FS'!I$53 -> 0.039437853 | J35: ='Historical FS'!J45/'Historical FS'!J$53 -> 0.058925455 | ... L35: ='Historical FS'!L45/'Historical FS'!L$53 -> 0.054656937
B36: ='Historical FS'!B46 -> Other Assets | C36: ='Historical FS'!C46/'Historical FS'!C$53 -> 0.11524258 | D36: ='Historical FS'!D46/'Historical FS'!D$53 -> 0.15071101 | E36: ='Historical FS'!E46/'Historical FS'!E$53 -> 0.14198293 | F36: ='Historical FS'!F46/'Historical FS'!F$53 -> 0.18821019 | G36: ='Historical FS'!G46/'Historical FS'!G$53 -> 0.058699447 | H36: ='Historical FS'!H46/'Historical FS'!H$53 -> 0.057030607 | I36: ='Historical FS'!I46/'Historical FS'!I$53 -> 0.059895726 | J36: ='Historical FS'!J46/'Historical FS'!J$53 -> 0.057549466 | ... L36: ='Historical FS'!L46/'Historical FS'!L$53 -> 0.071082857
B37: ='Historical FS'!B47 -> Total Non-Current Assets | C37: ='Historical FS'!C47/'Historical FS'!C$53 -> 0.65274417 | D37: ='Historical FS'!D47/'Historical FS'!D$53 -> 0.59086329 | E37: ='Historical FS'!E47/'Historical FS'!E$53 -> 0.5626711 | F37: ='Historical FS'!F47/'Historical FS'!F$53 -> 0.55197737 | G37: ='Historical FS'!G47/'Historical FS'!G$53 -> 0.85731743 | H37: ='Historical FS'!H47/'Historical FS'!H$53 -> 0.85564349 | I37: ='Historical FS'!I47/'Historical FS'!I$53 -> 0.83568017 | J37: ='Historical FS'!J47/'Historical FS'!J$53 -> 0.81426697 | ... L37: ='Historical FS'!L47/'Historical FS'!L$53 -> 0.85685625
B38: ='Historical FS'!B48 -> Receivables | C38: ='Historical FS'!C48/'Historical FS'!C$53 -> 0.06908188 | D38: ='Historical FS'!D48/'Historical FS'!D$53 -> 0.073340052 | E38: ='Historical FS'!E48/'Historical FS'!E$53 -> 0.09748242 | F38: ='Historical FS'!F48/'Historical FS'!F$53 -> 0.057013844 | G38: ='Historical FS'!G48/'Historical FS'!G$53 -> 0.025574629 | H38: ='Historical FS'!H48/'Historical FS'!H$53 -> 0.031713613 | I38: ='Historical FS'!I48/'Historical FS'!I$53 -> 0.04213364 | J38: ='Historical FS'!J48/'Historical FS'!J$53 -> 0.038183695 | ... L38: ='Historical FS'!L48/'Historical FS'!L$53 -> 0.042368843
B39: ='Historical FS'!B49 -> Inventory | C39: ='Historical FS'!C49/'Historical FS'!C$53 -> 0.1617853 | D39: ='Historical FS'!D49/'Historical FS'!D$53 -> 0.14068973 | E39: ='Historical FS'!E49/'Historical FS'!E$53 -> 0.13817167 | F39: ='Historical FS'!F49/'Historical FS'!F$53 -> 0.13729966 | G39: ='Historical FS'!G49/'Historical FS'!G$53 -> 0.052065755 | H39: ='Historical FS'!H49/'Historical FS'!H$53 -> 0.058094347 | I39: ='Historical FS'!I49/'Historical FS'!I$53 -> 0.058171518 | J39: ='Historical FS'!J49/'Historical FS'!J$53 -> 0.051242849 | ... L39: ='Historical FS'!L49/'Historical FS'!L$53 -> 0.060048651
B40: ='Historical FS'!B50 -> Cash & Bank | C40: ='Historical FS'!C50/'Historical FS'!C$53 -> 0.11638864 | D40: ='Historical FS'!D50/'Historical FS'!D$53 -> 0.19510693 | E40: ='Historical FS'!E50/'Historical FS'!E$53 -> 0.20167481 | F40: ='Historical FS'!F50/'Historical FS'!F$53 -> 0.25370913 | G40: ='Historical FS'!G50/'Historical FS'!G$53 -> 0.065042188 | H40: ='Historical FS'!H50/'Historical FS'!H$53 -> 0.054548549 | I40: ='Historical FS'!I50/'Historical FS'!I$53 -> 0.064014669 | J40: ='Historical FS'!J50/'Historical FS'!J$53 -> 0.096306489 | ... L40: ='Historical FS'!L50/'Historical FS'!L$53 -> 0.040726251
B41: ='Historical FS'!B51 -> Total Current Assets | C41: ='Historical FS'!C51/'Historical FS'!C$53 -> 0.34725583 | D41: ='Historical FS'!D51/'Historical FS'!D$53 -> 0.40913671 | E41: ='Historical FS'!E51/'Historical FS'!E$53 -> 0.4373289 | F41: ='Historical FS'!F51/'Historical FS'!F$53 -> 0.44802263 | G41: ='Historical FS'!G51/'Historical FS'!G$53 -> 0.14268257 | H41: ='Historical FS'!H51/'Historical FS'!H$53 -> 0.14435651 | I41: ='Historical FS'!I51/'Historical FS'!I$53 -> 0.16431983 | J41: ='Historical FS'!J51/'Historical FS'!J$53 -> 0.18573303 | ... L41: ='Historical FS'!L51/'Historical FS'!L$53 -> 0.14314375
B43: ='Historical FS'!B53 -> Total Assets | C43: ='Historical FS'!C53/'Historical FS'!C$53 -> 1 | D43: ='Historical FS'!D53/'Historical FS'!D$53 -> 1 | E43: ='Historical FS'!E53/'Historical FS'!E$53 -> 1 | F43: ='Historical FS'!F53/'Historical FS'!F$53 -> 1 | G43: ='Historical FS'!G53/'Historical FS'!G$53 -> 1 | H43: ='Historical FS'!H53/'Historical FS'!H$53 -> 1 | I43: ='Historical FS'!I53/'Historical FS'!I$53 -> 1 | J43: ='Historical FS'!J53/'Historical FS'!J$53 -> 1 | ... L43: ='Historical FS'!L53/'Historical FS'!L$53 -> 1

Sheet Trend Analysis
B2: ="Trend Analysis for "&'Data Sheet'!$B$1 -> Trend Analysis for HINDUSTAN UNILEVER LTD
B3: Year | C3: Revenue | D3: YoY Growth
B4: {=TRANSPOSE('Historical FS'!C3:P3)} -> 42825 | C4: {=TRANSPOSE('Historical FS'!C6:P6)} -> 33162 | D4: -
B5: 43190 | C5: 35545 | D5: =C5/C4-1 -> 0.071859357
B6: 43555 | C6: 39310 | D6: =C6/C5-1 -> 0.10592207
B7: 43921 | C7: 39783 | D7: =C7/C6-1 -> 0.012032562
B8: 44286 | C8: 47028 | D8: =C8/C7-1 -> 0.18211296
B9: 44651 | C9: 52446 | D9: =C9/C8-1 -> 0.11520796
B10: 45016 | C10: 60580 | D10: =C10/C9-1 -> 0.15509286
B11: 45382 | C11: 61896 | D11: =C11/C10-1 -> 0.021723341
B12: 45747 | C12: 63121 | D12: =C12/C11-1 -> 0.019791263
B13: 46112 | C13: 64468 | D13: =C13/C12-1 -> 0.021339966
B14: 46477 | C14: 71580.023 | D14: =C14/C13-1 -> 0.11031866
B15: 46842 | C15: 75897.69 | D15: =C15/C14-1 -> 0.06031944
B16: 47207 | C16: 80018.286 | D16: =C16/C15-1 -> 0.054291457
B17: 47572 | C17: 84102.444 | D17: =C17/C16-1 -> 0.051040306
B19: Why did the revenue growth fall from 2023 to 2024?
B20: Ans. Pricing Impact
B21: FY 2022-23 FMCG sales were supported more by price hikes, while FY 2023-24 had lower pricing tailwind and only modest volume growth.
B22: FY24 was a low-growth year for HUL because rural recovery was weak, inflation-fatigued consumers were slow to resume spending, and lower pricing power exposed the underlying softness in volumes.
